Workbook
Name NativeTimeline_Date: #N/A
Name NativeTimeline_Date1: #N/A
Name NativeTimeline_Date2: #N/A
Name Slicer_Category: #N/A
Name Slicer_Category1: #N/A
Name Slicer_Product: #N/A
Name Slicer_Profit: #N/A
Name Slicer_Region: #N/A
Name Slicer_Region1: #N/A
Name Slicer_Region2: #N/A
Name Slicer_Revenue: #N/A

Sheet Sheet6
A3: Products | B3: Sum of Revenue
A4: Headphones | B4: 22160
A5: Grand Total | B5: 22160

Sheet Sheet7
A3: Row Labels | B3: Sum of Revenue | C3: Sum of Profit | D3: Sum of Profit Margin %
A4: Headphones | B4: 92783 | C4: -1694 | D4: -0.018257655
A5: Laptop | B5: 100036 | C5: -70910 | D5: -0.70884482
A6: Monitor | B6: 100690 | C6: -25944 | D6: -0.25766213
A7: Printer | B7: 49991 | C7: -25089 | D7: -0.50187034
A8: Smartphone | B8: 37743 | C8: -36649 | D8: -0.97101449
A9: Tablet | B9: 60019 | C9: -80448 | D9: -1.3403755
A10: Grand Total | B10: 441262 | C10: -240734 | D10: -0.54555797

Sheet Sales_All
A1: OrderID | B1: Date | C1: Region | D1: CustomerID | E1: Product | F1: Quantity | G1: UnitPrice | H1: Category | I1: UnitCost | J1: Discount | K1: Revenue | L1: Discounted Revenue | M1: Profit | N1: Nested IFs | O1: Match & Index | P1: Dynamic Range | R1: DeliveryDays
A2: Q1-026 | B2: 45660.18 | C2: North | D2: 1009 | E2: Headphones | F2: 1 | G2: 1841 | H2: =_xlfn.XLOOKUP(E2, Products!A:A, Products!B:B, "Not Found") -> Accessories | I2: =_xlfn.XLOOKUP(E2, Products!A:A, Products!D:D, 0) -> 323 | J2: =_xlfn.XLOOKUP(E2, Products!A:A, Products!E:E, 0) -> 0.1 | K2: =SUM(F2*G2) -> 1841 | L2: =SUM(K2*(1-J2)) -> 1656.9 | M2: =ABS(K2- (Append1[[#This Row],[Quantity]]*Append1[[#This Row],[UnitCost]]) - Finance!B2) -> 24122 | N2: =IF(K2>50000, "VIP", IF(K2>=20000, "Regular", "Low Value")) -> Low Value | O2: =INDEX(E2:E91, MATCH(H2, H2:H91, 0)) -> Headphones | P2: {=OFFSET($H$2,0,0,COUNTA($H:$H)-1,2)} -> Accessories | Q2: 323 | R2: =_xlfn.XLOOKUP(A2, Operations!A:A, Operations!B:B, "") -> 3
A3: Q1-023 | B3: 45662.649 | C3: West | D3: 1006 | E3: Laptop | F3: 3 | G3: 1752 | H3: =_xlfn.XLOOKUP(E3, Products!A:A, Products!B:B, "Not Found") -> Electronics | I3: =_xlfn.XLOOKUP(E3, Products!A:A, Products!D:D, 0) -> 469 | J3: =_xlfn.XLOOKUP(E3, Products!A:A, Products!E:E, 0) -> 0.22 | K3: =SUM(F3*G3) -> 5256 | L3: =SUM(K3*(1-J3)) -> 4099.68 | M3: =SUM(K3- (Append1[[#This Row],[Quantity]]*Append1[[#This Row],[UnitCost]]) - Finance!B2) -> -21791 | N3: =IF(K3>50000, "VIP", IF(K3>=20000, "Regular", "Low Value")) -> Low Value | O3: =INDEX(E3:E92, MATCH(H3, H3:H92, 0)) -> Laptop | P3: Electronics | Q3: 469 | R3: =_xlfn.XLOOKUP(A3, Operations!A:A, Operations!B:B, "") -> 3
A4: Q1-012 | B4: 45662.79 | C4: South | D4: 1016 | E4: Laptop | F4: 3 | G4: 1692 | H4: =_xlfn.XLOOKUP(E4, Products!A:A, Products!B:B, "Not Found") -> Electronics | I4: =_xlfn.XLOOKUP(E4, Products!A:A, Products!D:D, 0) -> 469 | J4: =_xlfn.XLOOKUP(E4, Products!A:A, Products!E:E, 0) -> 0.22 | K4: =SUM(F4*G4) -> 5076 | L4: =SUM(K4*(1-J4)) -> 3959.28 | M4: =SUM(K4- (Append1[[#This Row],[Quantity]]*Append1[[#This Row],[UnitCost]]) - Finance!B2) -> -21971 | N4: =IF(K4>50000, "VIP", IF(K4>=20000, "Regular", "Low Value")) -> Low Value | O4: =INDEX(E4:E93, MATCH(H4, H4:H93, 0)) -> Laptop | P4: Electronics | Q4: 469 | R4: =_xlfn.XLOOKUP(A4, Operations!A:A, Operations!B:B, "") -> 8
A5: Q1-005 | B5: 45663.686 | C5: North | D5: 1012 | E5: Laptop | F5: 2 | G5: 709 | H5: =_xlfn.XLOOKUP(E5, Products!A:A, Products!B:B, "Not Found") -> Electronics | I5: =_xlfn.XLOOKUP(E5, Products!A:A, Products!D:D, 0) -> 469 | J5: =_xlfn.XLOOKUP(E5, Products!A:A, Products!E:E, 0) -> 0.22 | K5: =SUM(F5*G5) -> 1418 | L5: =SUM(K5*(1-J5)) -> 1106.04 | M5: =SUM(K5- (Append1[[#This Row],[Quantity]]*Append1[[#This Row],[UnitCost]]) - Finance!B2) -> -25160 | N5: =IF(K5>50000, "VIP", IF(K5>=20000, "Regular", "Low Value")) -> Low Value | O5: =INDEX(E5:E94, MATCH(H5, H5:H94, 0)) -> Laptop | P5: Electronics | Q5: 469 | R5: =_xlfn.XLOOKUP(A5, Operations!A:A, Operations!B:B, "") -> 5
A6: Q1-030 | B6: 45666.628 | C6: East | D6: 1016 | E6: Monitor | F6: 5 | G6: 1119 | H6: =_xlfn.XLOOKUP(E6, Products!A:A, Products!B:B, "Not Found") -> Electronics | I6: =_xlfn.XLOOKUP(E6, Products!A:A, Products!D:D, 0) -> 463 | J6: =_xlfn.XLOOKUP(E6, Products!A:A, Products!E:E, 0) -> 0.23 | K6: =SUM(F6*G6) -> 5595 | L6: =SUM(K6*(1-J6)) -> 4308.15 | M6: =SUM(K6- (Append1[[#This Row],[Quantity]]*Append1[[#This Row],[UnitCost]]) - Finance!B2) -> -22360 | N6: =IF(K6>50000, "VIP", IF(K6>=20000, "Regular", "Low Value")) -> Low Value | O6: =INDEX(E6:E95, MATCH(H6, H6:H95, 0)) -> Monitor | P6: Electronics | Q6: 463 | R6: =_xlfn.XLOOKUP(A6, Operations!A:A, Operations!B:B, "") -> 2
A7: Q1-009 | B7: 45671.497 | C7: South | D7: 1020 | E7: Printer | F7: 1 | G7: 1220 | H7: =_xlfn.XLOOKUP(E7, Products!A:A, Products!B:B, "Not Found") -> Office | I7: =_xlfn.XLOOKUP(E7, Products!A:A, Products!D:D, 0) -> 136 | J7: =_xlfn.XLOOKUP(E7, Products!A:A, Products!E:E, 0) -> 0.1 | K7: =SUM(F7*G7) -> 1220 | L7: =SUM(K7*(1-J7)) -> 1098 | M7: =SUM(K7- (Append1[[#This Row],[Quantity]]*Append1[[#This Row],[UnitCost]]) - Finance!B2) -> -24556 | N7: =IF(K7>50000, "VIP", IF(K7>=20000, "Regular", "Low Value")) -> Low Value | O7: =INDEX(E7:E96, MATCH(H7, H7:H96, 0)) -> Printer | P7: Office | Q7: 136 | R7: =_xlfn.XLOOKUP(A7, Operations!A:A, Operations!B:B, "") -> 2
A8: Q1-015 | B8: 45672.073 | C8: South | D8: 1016 | E8: Monitor | F8: 3 | G8: 1355 | H8: =_xlfn.XLOOKUP(E8, Products!A:A, Products!B:B, "Not Found") -> Electronics | I8: =_xlfn.XLOOKUP(E8, Products!A:A, Products!D:D, 0) -> 463 | J8: =_xlfn.XLOOKUP(E8, Products!A:A, Products!E:E, 0) -> 0.23 | K8: =SUM(F8*G8) -> 4065 | L8: =SUM(K8*(1-J8)) -> 3130.05 | M8: =SUM(K8- (Append1[[#This Row],[Quantity]]*Append1[[#This Row],[UnitCost]]) - Finance!B2) -> -22964 | N8: =IF(K8>50000, "VIP", IF(K8>=20000, "Regular", "Low Value")) -> Low Value | O8: =INDEX(E8:E97, MATCH(H8, H8:H97, 0)) -> Monitor | P8: Electronics | Q8: 463 | R8: =_xlfn.XLOOKUP(A8, Operations!A:A, Operations!B:B, "") -> 4
A9: Q1-011 | B9: 45684.929 | C9: West | D9: 1019 | E9: Laptop | F9: 9 | G9: 417 | H9: =_xlfn.XLOOKUP(E9, Products!A:A, Products!B:B, "Not Found") -> Electronics | I9: =_xlfn.XLOOKUP(E9, Products!A:A, Products!D:D, 0) -> 469 | J9: =_xlfn.XLOOKUP(E9, Products!A:A, Products!E:E, 0) -> 0.22 | K9: =SUM(F9*G9) -> 3753 | L9: =SUM(K9*(1-J9)) -> 2927.34 | M9: =SUM(K9- (Append1[[#This Row],[Quantity]]*Append1[[#This Row],[UnitCost]]) - Finance!B2) -> -26108 | N9: =IF(K9>50000, "VIP", IF(K9>=20000, "Regular", "Low Value")) -> Low Value | O9: =INDEX(E9:E98, MATCH(H9, H9:H98, 0)) -> Laptop | P9: Electronics | Q9: 469 | R9: =_xlfn.XLOOKUP(A9, Operations!A:A, Operations!B:B, "") -> 8
A10: Q1-028 | B10: 45685.124 | C10: West | D10: 1003 | E10: Monitor | F10: 6 | G10: 1011 | H10: =_xlfn.XLOOKUP(E10, Products!A:A, Products!B:B, "Not Found") -> Electronics | I10: =_xlfn.XLOOKUP(E10, Products!A:A, Products!D:D, 0) -> 463 | J10: =_xlfn.XLOOKUP(E10, Products!A:A, Products!E:E, 0) -> 0.23 | K10: =SUM(F10*G10) -> 6066 | L10: =SUM(K10*(1-J10)) -> 4670.82 | M10: =SUM(K10- (Append1[[#This Row],[Quantity]]*Append1[[#This Row],[UnitCost]]) - Finance!B30) -> 3288 | N10: =IF(K10>50000, "VIP", IF(K10>=20000, "Regular", "Low Value")) -> Low Value | O10: =INDEX(E10:E99, MATCH(H10, H10:H99, 0)) -> Monitor | P10: Electronics | Q10: 463 | R10: =_xlfn.XLOOKUP(A10, Operations!A:A, Operations!B:B, "") -> 2
A11: Q1-017 | B11: 45688.214 | C11: North | D11: 1008 | E11: Smartphone | F11: 3 | G11: 605 | H11: =_xlfn.XLOOKUP(E11, Products!A:A, Products!B:B, "Not Found") -> Electronics | I11: =_xlfn.XLOOKUP(E11, Products!A:A, Products!D:D, 0) -> 97 | J11: =_xlfn.XLOOKUP(E11, Products!A:A, Products!E:E, 0) -> 0.08 | K11: =SUM(F11*G11) -> 1815 | L11: =SUM(K11*(1-J11)) -> 1669.8 | M11: =SUM(K11- (Append1[[#This Row],[Quantity]]*Append1[[#This Row],[UnitCost]]) - Finance!B2) -> -24116 | N11: =IF(K11>50000, "VIP", IF(K11>=20000, "Regular", "Low Value")) -> Low Value | O11: =INDEX(E11:E100, MATCH(H11, H11:H100, 0)) -> Smartphone | P11: Electronics | Q11: 97 | R11: =_xlfn.XLOOKUP(A11, Operations!A:A, Operations!B:B, "") -> 6
A12: Q1-013 | B12: 45693.46 | C12: East | D12: 1001 | E12: Printer | F12: 4 | G12: 1853 | H12: =_xlfn.XLOOKUP(E12, Products!A:A, Products!B:B, "Not Found") -> Office | I12: =_xlfn.XLOOKUP(E12, Products!A:A, Products!D:D, 0) -> 136 | J12: =_xlfn.XLOOKUP(E12, Products!A:A, Products!E:E, 0) -> 0.1 | K12: =SUM(F12*G12) -> 7412 | L12: =SUM(K12*(1-J12)) -> 6670.8 | M12: =SUM(K12- (Append1[[#This Row],[Quantity]]*Append1[[#This Row],[UnitCost]]) - Finance!B3) -> -36452 | N12: =IF(K12>50000, "VIP", IF(K12>=20000, "Regular", "Low Value")) -> Low Value | O12: =INDEX(E12:E101, MATCH(H12, H12:H101, 0)) -> Printer | P12: Office | Q12: 136 | R12: =_xlfn.XLOOKUP(A12, Operations!A:A, Operations!B:B, "") -> 1
A13: Q1-019 | B13: 45696.452 | C13: North | D13: 1010 | E13: Headphones | F13: 1 | G13: 1621 | H13: =_xlfn.XLOOKUP(E13, Products!A:A, Products!B:B, "Not Found") -> Accessories | I13: =_xlfn.XLOOKUP(E13, Products!A:A, Products!D:D, 0) -> 323 | J13: =_xlfn.XLOOKUP(E13, Products!A:A, Products!E:E, 0) -> 0.1 | K13: =SUM(F13*G13) -> 1621 | L13: =SUM(K13*(1-J13)) -> 1458.9 | M13: =SUM(K13- (Append1[[#This Row],[Quantity]]*Append1[[#This Row],[UnitCost]]) - Finance!B21) -> 1298 | N13: =IF(K13>50000, "VIP", IF(K13>=20000, "Regular", "Low Value")) -> Low Value | O13: =INDEX(E13:E102, MATCH(H13, H13:H102, 0)) -> Headphones | P13: Accessories | Q13: 323 | R13: =_xlfn.XLOOKUP(A13, Operations!A:A, Operations!B:B, "") -> 2
A14: Q1-004 | B14: 45703.571 | C14: East | D14: 1018 | E14: Smartphone | F14: 8 | G14: 726 | H14: =_xlfn.XLOOKUP(E14, Products!A:A, Products!B:B, "Not Found") -> Electronics | I14: =_xlfn.XLOOKUP(E14, Products!A:A, Products!D:D, 0) -> 97 | J14: =_xlfn.XLOOKUP(E14, Products!A:A, Products!E:E, 0) -> 0.08 | K14: =SUM(F14*G14) -> 5808 | L14: =SUM(K14*(1-J14)) -> 5343.36 | M14: =SUM(K14- (Append1[[#This Row],[Quantity]]*Append1[[#This Row],[UnitCost]]) - Finance!B3) -> -38288 | N14: =IF(K14>50000, "VIP", IF(K14>=20000, "Regular", "Low Value")) -> Low Value | O14: =INDEX(E14:E103, MATCH(H14, H14:H103, 0)) -> Smartphone | P14: Electronics | Q14: 97 | R14: =_xlfn.XLOOKUP(A14, Operations!A:A, Operations!B:B, "") -> 4
A15: Q1-008 | B15: 45707.394 | C15: South | D15: 1014 | E15: Tablet | F15: 5 | G15: 1134 | H15: =_xlfn.XLOOKUP(E15, Products!A:A, Products!B:B, "Not Found") -> Electronics | I15: =_xlfn.XLOOKUP(E15, Products!A:A, Products!D:D, 0) -> 492 | J15: =_xlfn.XLOOKUP(E15, Products!A:A, Products!E:E, 0) -> 0.14 | K15: =SUM(F15*G15) -> 5670 | L15: =SUM(K15*(1-J15)) -> 4876.2 | M15: =SUM(K15- (Append1[[#This Row],[Quantity]]*Append1[[#This Row],[UnitCost]]) - Finance!B3) -> -40110 | N15: =IF(K15>50000, "VIP", IF(K15>=20000, "Regular", "Low Value")) -> Low Value | O15: =INDEX(E15:E104, MATCH(H15, H15:H104, 0)) -> Tablet | P15: Electronics | Q15: 492 | R15: =_xlfn.XLOOKUP(A15, Operations!A:A, Operations!B:B, "") -> 8
A16: Q1-001 | B16: 45708.027 | C16: South | D16: 1018 | E16: Tablet | F16: 1 | G16: 730 | H16: =_xlfn.XLOOKUP(E16, Products!A:A, Products!B:B, "Not Found") -> Electronics | I16: =_xlfn.XLOOKUP(E16, Products!A:A, Products!D:D, 0) -> 492 | J16: =_xlfn.XLOOKUP(E16, Products!A:A, Products!E:E, 0) -> 0.14 | K16: =SUM(F16*G16) -> 730 | L16: =SUM(K16*(1-J16)) -> 627.8 | M16: =SUM(K16- (Append1[[#This Row],[Quantity]]*Append1[[#This Row],[UnitCost]]) - Finance!B3) -> -43082 | N16: =IF(K16>50000, "VIP", IF(K16>=20000, "Regular", "Low Value")) -> Low Value | O16: =INDEX(E16:E105, MATCH(H16, H16:H105, 0)) -> Tablet | P16: Electronics | Q16: 492 | R16: =_xlfn.XLOOKUP(A16, Operations!A:A, Operations!B:B, "") -> 5
A17: Q1-025 | B17: 45710.772 | C17: South | D17: 1007 | E17: Monitor | F17: 8 | G17: 1770 | H17: =_xlfn.XLOOKUP(E17, Products!A:A, Products!B:B, "Not Found") -> Electronics | I17: =_xlfn.XLOOKUP(E17, Products!A:A, Products!D:D, 0) -> 463 | J17: =_xlfn.XLOOKUP(E17, Products!A:A, Products!E:E, 0) -> 0.23 | K17: =SUM(F17*G17) -> 14160 | L17: =SUM(K17*(1-J17)) -> 10903.2 | M17: =SUM(K17- (Append1[[#This Row],[Quantity]]*Append1[[#This Row],[UnitCost]]) - Finance!B27) -> 10456 | N17: =IF(K17>50000, "VIP", IF(K17>=20000, "Regular", "Low Value")) -> Low Value | O17: =INDEX(E17:E106, MATCH(H17, H17:H106, 0)) -> Monitor | P17: Electronics | Q17: 463 | R17: =_xlfn.XLOOKUP(A17, Operations!A:A, Operations!B:B, "") -> 9
A18: Q1-002 | B18: 45712.237 | C18: South | D18: 1004 | E18: Headphones | F18: 3 | G18: 378 | H18: =_xlfn.XLOOKUP(E18, Products!A:A, Products!B:B, "Not Found") -> Accessories | I18: =_xlfn.XLOOKUP(E18, Products!A:A, Products!D:D, 0) -> 323 | J18: =_xlfn.XLOOKUP(E18, Products!A:A, Products!E:E, 0) -> 0.1 | K18: =SUM(F18*G18) -> 1134 | L18: =SUM(K18*(1-J18)) -> 1020.6 | M18: =SUM(K18- (Append1[[#This Row],[Quantity]]*Append1[[#This Row],[UnitCost]]) - Finance!B3) -> -43155 | N18: =IF(K18>50000, "VIP", IF(K18>=20000, "Regular", "Low Value")) -> Low Value | O18: =INDEX(E18:E107, MATCH(H18, H18:H107, 0)) -> Headphones | P18: Accessories | Q18: 323 | R18: =_xlfn.XLOOKUP(A18, Operations!A:A, Operations!B:B, "") -> 2
A19: Q1-021 | B19: 45713.211 | C19: South | D19: 1008 | E19: Headphones | F19: 7 | G19: 241 | H19: =_xlfn.XLOOKUP(E19, Products!A:A, Products!B:B, "Not Found") -> Accessories | I19: =_xlfn.XLOOKUP(E19, Products!A:A, Products!D:D, 0) -> 323 | J19: =_xlfn.XLOOKUP(E19, Products!A:A, Products!E:E, 0) -> 0.1 | K19: =SUM(F19*G19) -> 1687 | L19: =SUM(K19*(1-J19)) -> 1518.3 | M19: =SUM(K19- (Append1[[#This Row],[Quantity]]*Append1[[#This Row],[UnitCost]]) - Finance!B23) -> -574 | N19: =IF(K19>50000, "VIP", IF(K19>=20000, "Regular", "Low Value")) -> Low Value | O19: =INDEX(E19:E108, MATCH(H19, H19:H108, 0)) -> Headphones | P19: Accessories | Q19: 323 | R19: =_xlfn.XLOOKUP(A19, Operations!A:A, Operations!B:B, "") -> 8
A20: Q1-024 | B20: 45715.878 | C20: East | D20: 1020 | E20: Headphones | F20: 8 | G20: 911 | H20: =_xlfn.XLOOKUP(E20, Products!A:A, Products!B:B, "Not Found") -> Accessories | I20: =_xlfn.XLOOKUP(E20, Products!A:A, Products!D:D, 0) -> 323 | J20: =_xlfn.XLOOKUP(E20, Products!A:A, Products!E:E, 0) -> 0.1 | K20: =SUM(F20*G20) -> 7288 | L20: =SUM(K20*(1-J20)) -> 6559.2 | M20: =SUM(K20- (Append1[[#This Row],[Quantity]]*Append1[[#This Row],[UnitCost]]) - Finance!B26) -> 4704 | N20: =IF(K20>50000, "VIP", IF(K20>=20000, "Regular", "Low Value")) -> Low Value | O20: =INDEX(E20:E109, MATCH(H20, H20:H109, 0)) -> Headphones | P20: Accessories | Q20: 323 | R20: =_xlfn.XLOOKUP(A20, Operations!A:A, Operations!B:B, "") -> 1
A21: Q1-006 | B21: 45716.227 | C21: East | D21: 1013 | E21: Laptop | F21: 8 | G21: 1817 | H21: =_xlfn.XLOOKUP(E21, Products!A:A, Products!B:B, "Not Found") -> Electronics | I21: =_xlfn.XLOOKUP(E21, Products!A:A, Products!D:D, 0) -> 469 | J21: =_xlfn.XLOOKUP(E21, Products!A:A, Products!E:E, 0) -> 0.22 | K21: =SUM(F21*G21) -> 14536 | L21: =SUM(K21*(1-J21)) -> 11338.08 | M21: =SUM(K21- (Append1[[#This Row],[Quantity]]*Append1[[#This Row],[UnitCost]]) - Finance!B7) -> -9295 | N21: =IF(K21>50000, "VIP", IF(K21>=20000, "Regular", "Low Value")) -> Low Value | O21: =INDEX(E21:E110, MATCH(H21, H21:H110, 0)) -> Laptop | P21: Electronics | Q21: 469 | R21: =_xlfn.XLOOKUP(A21, Operations!A:A, Operations!B:B, "") -> 5
A22: Q1-014 | B22: 45717.254 | C22: South | D22: 1005 | E22: Printer | F22: 2 | G22: 505 | H22: =_xlfn.XLOOKUP(E22, Products!A:A, Products!B:B, "Not Found") -> Office | I22: =_xlfn.XLOOKUP(E22, Products!A:A, Products!D:D, 0) -> 136 | J22: =_xlfn.XLOOKUP(E22, Products!A:A, Products!E:E, 0) -> 0.1 | K22: =SUM(F22*G22) -> 1010 | L22: =SUM(K22*(1-J22)) -> 909 | M22: =SUM(K22- (Append1[[#This Row],[Quantity]]*Append1[[#This Row],[UnitCost]]) - Finance!B16) -> 738 | N22: =IF(K22>50000, "VIP", IF(K22>=20000, "Regular", "Low Value")) -> Low Value | O22: =INDEX(E22:E111, MATCH(H22, H22:H111, 0)) -> Printer | P22: Office | Q22: 136 | R22: =_xlfn.XLOOKUP(A22, Operations!A:A, Operations!B:B, "") -> 3
A23: Q1-027 | B23: 45718.188 | C23: East | D23: 1001 | E23: Monitor | F23: 7 | G23: 796 | H23: =_xlfn.XLOOKUP(E23, Products!A:A, Products!B:B, "Not Found") -> Electronics | I23: =_xlfn.XLOOKUP(E23, Products!A:A, Products!D:D, 0) -> 463 | J23: =_xlfn.XLOOKUP(E23, Products!A:A, Products!E:E, 0) -> 0.23 | K23: =SUM(F23*G23) -> 5572 | L23: =SUM(K23*(1-J23)) -> 4290.44 | M23: =SUM(K23- (Append1[[#This Row],[Quantity]]*Append1[[#This Row],[UnitCost]]) - Finance!B29) -> 2331 | N23: =IF(K23>50000, "VIP", IF(K23>=20000, "Regular", "Low Value")) -> Low Value | O23: =INDEX(E23:E112, MATCH(H23, H23:H112, 0)) -> Monitor | P23: Electronics | Q23: 463 | R23: =_xlfn.XLOOKUP(A23, Operations!A:A, Operations!B:B, "") -> 6
A24: Q1-018 | B24: 45718.933 | C24: South | D24: 1009 | E24: Monitor | F24: 7 | G24: 1149 | H24: =_xlfn.XLOOKUP(E24, Products!A:A, Products!B:B, "Not Found") -> Electronics | I24: =_xlfn.XLOOKUP(E24, Products!A:A, Products!D:D, 0) -> 463 | J24: =_xlfn.XLOOKUP(E24, Products!A:A, Products!E:E, 0) -> 0.23 | K24: =SUM(F24*G24) -> 8043 | L24: =SUM(K24*(1-J24)) -> 6193.11 | M24: =SUM(K24- (Append1[[#This Row],[Quantity]]*Append1[[#This Row],[UnitCost]]) - Finance!B20) -> 4802 | N24: =IF(K24>50000, "VIP", IF(K24>=20000, "Regular", "Low Value")) -> Low Value | O24: =INDEX(E24:E113, MATCH(H24, H24:H113, 0)) -> Monitor | P24: Electronics | Q24: 463 | R24: =_xlfn.XLOOKUP(A24, Operations!A:A, Operations!B:B, "") -> 9
A25: Q1-029 | B25: 45722.085 | C25: West | D25: 1011 | E25: Printer | F25: 2 | G25: 1660 | H25: =_xlfn.XLOOKUP(E25, Products!A:A, Products!B:B, "Not Found") -> Office | I25: =_xlfn.XLOOKUP(E25, Products!A:A, Products!D:D, 0) -> 136 | J25: =_xlfn.XLOOKUP(E25, Products!A:A, Products!E:E, 0) -> 0.1 | K25: =SUM(F25*G25) -> 3320 | L25: =SUM(K25*(1-J25)) -> 2988 | M25: =SUM(K25- (Append1[[#This Row],[Quantity]]*Append1[[#This Row],[UnitCost]]) - Finance!B31) -> 3048 | N25: =IF(K25>50000, "VIP", IF(K25>=20000, "Regular", "Low Value")) -> Low Value | O25: =INDEX(E25:E114, MATCH(H25, H25:H114, 0)) -> Printer | P25: Office | Q25: 136 | R25: =_xlfn.XLOOKUP(A25, Operations!A:A, Operations!B:B, "") -> 9
A26: Q1-022 | B26: 45723.978 | C26: West | D26: 1005 | E26: Printer | F26: 7 | G26: 1336 | H26: =_xlfn.XLOOKUP(E26, Products!A:A, Products!B:B, "Not Found") -> Office | I26: =_xlfn.XLOOKUP(E26, Products!A:A, Products!D:D, 0) -> 136 | J26: =_xlfn.XLOOKUP(E26, Products!A:A, Products!E:E, 0) -> 0.1 | K26: =SUM(F26*G26) -> 9352 | L26: =SUM(K26*(1-J26)) -> 8416.8 | M26: =SUM(K26- (Append1[[#This Row],[Quantity]]*Append1[[#This Row],[UnitCost]]) - Finance!B24) -> 8400 | N26: =IF(K26>50000, "VIP", IF(K26>=20000, "Regular", "Low Value")) -> Low Value | O26: =INDEX(E26:E115, MATCH(H26, H26:H115, 0)) -> Printer | P26: Office | Q26: 136 | R26: =_xlfn.XLOOKUP(A26, Operations!A:A, Operations!B:B, "") -> 7
A27: Q1-007 | B27: 45735.116 | C27: South | D27: 1017 | E27: Tablet | F27: 9 | G27: 1976 | H27: =_xlfn.XLOOKUP(E27, Products!A:A, Products!B:B, "Not Found") -> Electronics | I27: =_xlfn.XLOOKUP(E27, Products!A:A, Products!D:D, 0) -> 492 | J27: =_xlfn.XLOOKUP(E27, Products!A:A, Products!E:E, 0) -> 0.14 | K27: =SUM(F27*G27) -> 17784 | L27: =SUM(K27*(1-J27)) -> 15294.24 | M27: =SUM(K27- (Append1[[#This Row],[Quantity]]*Append1[[#This Row],[UnitCost]]) - Finance!B4) -> -20791 | N27: =IF(K27>50000, "VIP", IF(K27>=20000, "Regular", "Low Value")) -> Low Value | O27: =INDEX(E27:E116, MATCH(H27, H27:H116, 0)) -> Tablet | P27: Electronics | Q27: 492 | R27: =_xlfn.XLOOKUP(A27, Operations!A:A, Operations!B:B, "") -> 4
A28: Q1-003 | B28: 45736.268 | C28: West | D28: 1005 | E28: Monitor | F28: 1 | G28: 585 | H28: =_xlfn.XLOOKUP(E28, Products!A:A, Products!B:B, "Not Found") -> Electronics | I28: =_xlfn.XLOOKUP(E28, Products!A:A, Products!D:D, 0) -> 463 | J28: =_xlfn.XLOOKUP(E28, Products!A:A, Products!E:E, 0) -> 0.23 | K28: =SUM(F28*G28) -> 585 | L28: =SUM(K28*(1-J28)) -> 450.45 | M28: =SUM(K28- (Append1[[#This Row],[Quantity]]*Append1[[#This Row],[UnitCost]]) - Finance!B4) -> -34025 | N28: =IF(K28>50000, "VIP", IF(K28>=20000, "Regular", "Low Value")) -> Low Value | O28: =INDEX(E28:E117, MATCH(H28, H28:H117, 0)) -> Monitor | P28: Electronics | Q28: 463 | R28: =_xlfn.XLOOKUP(A28, Operations!A:A, Operations!B:B, "") -> 6
A29: Q1-020 | B29: 45738.817 | C29: North | D29: 1004 | E29: Printer | F29: 3 | G29: 1010 | H29: =_xlfn.XLOOKUP(E29, Products!A:A, Products!B:B, "Not Found") -> Office | I29: =_xlfn.XLOOKUP(E29, Products!A:A, Products!D:D, 0) -> 136 | J29: =_xlfn.XLOOKUP(E29, Products!A:A, Products!E:E, 0) -> 0.1 | K29: =SUM(F29*G29) -> 3030 | L29: =SUM(K29*(1-J29)) -> 2727 | M29: =SUM(K29- (Append1[[#This Row],[Quantity]]*Append1[[#This Row],[UnitCost]]) - Finance!B22) -> 2622 | N29: =IF(K29>50000, "VIP", IF(K29>=20000, "Regular", "Low Value")) -> Low Value | O29: =INDEX(E29:E118, MATCH(H29, H29:H118, 0)) -> Printer | P29: Office | Q29: 136 | R29: =_xlfn.XLOOKUP(A29, Operations!A:A, Operations!B:B, "") -> 1
A30: Q1-016 | B30: 45742.873 | C30: North | D30: 1003 | E30: Printer | F30: 8 | G30: 1220 | H30: =_xlfn.XLOOKUP(E30, Products!A:A, Products!B:B, "Not Found") -> Office | I30: =_xlfn.XLOOKUP(E30, Products!A:A, Products!D:D, 0) -> 136 | J30: =_xlfn.XLOOKUP(E30, Products!A:A, Products!E:E, 0) -> 0.1 | K30: =SUM(F30*G30) -> 9760 | L30: =SUM(K30*(1-J30)) -> 8784 | M30: =SUM(K30- (Append1[[#This Row],[Quantity]]*Append1[[#This Row],[UnitCost]]) - Finance!B18) -> 8672 | N30: =IF(K30>50000, "VIP", IF(K30>=20000, "Regular", "Low Value")) -> Low Value | O30: =INDEX(E30:E119, MATCH(H30, H30:H119, 0)) -> Printer | P30: Office | Q30: 136 | R30: =_xlfn.XLOOKUP(A30, Operations!A:A, Operations!B:B, "") -> 3
A31: Q1-010 | B31: 45743.202 | C31: West | D31: 1010 | E31: Headphones | F31: 2 | G31: 283 | H31: =_xlfn.XLOOKUP(E31, Products!A:A, Products!B:B, "Not Found") -> Accessories | I31: =_xlfn.XLOOKUP(E31, Products!A:A, Products!D:D, 0) -> 323 | J31: =_xlfn.XLOOKUP(E31, Products!A:A, Products!E:E, 0) -> 0.1 | K31: =SUM(F31*G31) -> 566 | L31: =SUM(K31*(1-J31)) -> 509.4 | M31: =SUM(K31- (Append1[[#This Row],[Quantity]]*Append1[[#This Row],[UnitCost]]) - Finance!B12) -> -80 | N31: =IF(K31>50000, "VIP", IF(K31>=20000, "Regular", "Low Value")) -> Low Value | O31: =INDEX(E31:E120, MATCH(H31, H31:H120, 0)) -> Headphones | P31: Accessories | Q31: 323 | R31: =_xlfn.XLOOKUP(A31, Operations!A:A, Operations!B:B, "") -> 2
A32: Q2-019 | B32: 45749.993 | C32: North | D32: 1010 | E32: Printer | F32: 1 | G32: 648 | H32: =_xlfn.XLOOKUP(E32, Products!A:A, Products!B:B, "Not Found") -> Office | I32: =_xlfn.XLOOKUP(E32, Products!A:A, Products!D:D, 0) -> 136 | J32: =_xlfn.XLOOKUP(E32, Products!A:A, Products!E:E, 0) -> 0.1 | K32: =SUM(F32*G32) -> 648 | L32: =SUM(K32*(1-J32)) -> 583.2 | M32: =SUM(K32- (Append1[[#This Row],[Quantity]]*Append1[[#This Row],[UnitCost]]) - Finance!B51) -> 512 | N32: =IF(K32>50000, "VIP", IF(K32>=20000, "Regular", "Low Value")) -> Low Value | O32: =INDEX(E32:E121, MATCH(H32, H32:H121, 0)) -> Printer | P32: Office | Q32: 136 | R32: =_xlfn.XLOOKUP(A32, Operations!A:A, Operations!B:B, "") -> 8
A33: Q2-030 | B33: 45752.783 | C33: East | D33: 1006 | E33: Headphones | F33: 2 | G33: 1035 | H33: =_xlfn.XLOOKUP(E33, Products!A:A, Products!B:B, "Not Found") -> Accessories | I33: =_xlfn.XLOOKUP(E33, Products!A:A, Products!D:D, 0) -> 323 | J33: =_xlfn.XLOOKUP(E33, Products!A:A, Products!E:E, 0) -> 0.1 | K33: =SUM(F33*G33) -> 2070 | L33: =SUM(K33*(1-J33)) -> 1863 | M33: =SUM(K33- (Append1[[#This Row],[Quantity]]*Append1[[#This Row],[UnitCost]]) - Finance!B62) -> 1424 | N33: =IF(K33>50000, "VIP", IF(K33>=20000, "Regular", "Low Value")) -> Low Value | O33: =INDEX(E33:E122, MATCH(H33, H33:H122, 0)) -> Headphones | P33: Accessories | Q33: 323 | R33: =_xlfn.XLOOKUP(A33, Operations!A:A, Operations!B:B, "") -> 8
A34: Q2-011 | B34: 45754.452 | C34: South | D34: 1012 | E34: Headphones | F34: 3 | G34: 1781 | H34: =_xlfn.XLOOKUP(E34, Products!A:A, Products!B:B, "Not Found") -> Accessories | I34: =_xlfn.XLOOKUP(E34, Products!A:A, Products!D:D, 0) -> 323 | J34: =_xlfn.XLOOKUP(E34, Products!A:A, Products!E:E, 0) -> 0.1 | K34: =SUM(F34*G34) -> 5343 | L34: =SUM(K34*(1-J34)) -> 4808.7 | M34: =SUM(K34- (Append1[[#This Row],[Quantity]]*Append1[[#This Row],[UnitCost]]) - Finance!B43) -> 4374 | N34: =IF(K34>50000, "VIP", IF(K34>=20000, "Regular", "Low Value")) -> Low Value | O34: =INDEX(E34:E123, MATCH(H34, H34:H123, 0)) -> Headphones | P34: Accessories | Q34: 323 | R34: =_xlfn.XLOOKUP(A34, Operations!A:A, Operations!B:B, "") -> 5
A35: Q2-014 | B35: 45754.48 | C35: North | D35: 1009 | E35: Laptop | F35: 8 | G35: 1539 | H35: =_xlfn.XLOOKUP(E35, Products!A:A, Products!B:B, "Not Found") -> Electronics | I35: =_xlfn.XLOOKUP(E35, Products!A:A, Products!D:D, 0) -> 469 | J35: =_xlfn.XLOOKUP(E35, Products!A:A, Products!E:E, 0) -> 0.22 | K35: =SUM(F35*G35) -> 12312 | L35: =SUM(K35*(1-J35)) -> 9603.36 | M35: =SUM(K35- (Append1[[#This Row],[Quantity]]*Append1[[#This Row],[UnitCost]]) - Finance!B46) -> 8560 | N35: =IF(K35>50000, "VIP", IF(K35>=20000, "Regular", "Low Value")) -> Low Value | O35: =INDEX(E35:E124, MATCH(H35, H35:H124, 0)) -> Laptop | P35: Electronics | Q35: 469 | R35: =_xlfn.XLOOKUP(A35, Operations!A:A, Operations!B:B, "") -> 4
A36: Q2-026 | B36: 45756.893 | C36: East | D36: 1005 | E36: Printer | F36: 2 | G36: 109 | H36: =_xlfn.XLOOKUP(E36, Products!A:A, Products!B:B, "Not Found") -> Office | I36: =_xlfn.XLOOKUP(E36, Products!A:A, Products!D:D, 0) -> 136 | J36: =_xlfn.XLOOKUP(E36, Products!A:A, Products!E:E, 0) -> 0.1 | K36: =SUM(F36*G36) -> 218 | L36: =SUM(K36*(1-J36)) -> 196.2 | M36: =SUM(K36- (Append1[[#This Row],[Quantity]]*Append1[[#This Row],[UnitCost]]) - Finance!B58) -> -54 | N36: =IF(K36>50000, "VIP", IF(K36>=20000, "Regular", "Low Value")) -> Low Value | O36: =INDEX(E36:E125, MATCH(H36, H36:H125, 0)) -> Printer | P36: Office | Q36: 136 | R36: =_xlfn.XLOOKUP(A36, Operations!A:A, Operations!B:B, "") -> 2
A37: Q2-009 | B37: 45759.132 | C37: West | D37: 1020 | E37: Laptop | F37: 8 | G37: 1331 | H37: =_xlfn.XLOOKUP(E37, Products!A:A, Products!B:B, "Not Found") -> Electronics | I37: =_xlfn.XLOOKUP(E37, Products!A:A, Products!D:D, 0) -> 469 | J37: =_xlfn.XLOOKUP(E37, Products!A:A, Products!E:E, 0) -> 0.22 | K37: =SUM(F37*G37) -> 10648 | L37: =SUM(K37*(1-J37)) -> 8305.44 | M37: =SUM(K37- (Append1[[#This Row],[Quantity]]*Append1[[#This Row],[UnitCost]]) - Finance!B41) -> 6896 | N37: =IF(K37>50000, "VIP", IF(K37>=20000, "Regular", "Low Value")) -> Low Value | O37: =INDEX(E37:E126, MATCH(H37, H37:H126, 0)) -> Laptop | P37: Electronics | Q37: 469 | R37: =_xlfn.XLOOKUP(A37, Operations!A:A, Operations!B:B, "") -> 7
A38: Q2-010 | B38: 45760.76 | C38: West | D38: 1001 | E38: Smartphone | F38: 2 | G38: 222 | H38: =_xlfn.XLOOKUP(E38, Products!A:A, Products!B:B, "Not Found") -> Electronics | I38: =_xlfn.XLOOKUP(E38, Products!A:A, Products!D:D, 0) -> 97 | J38: =_xlfn.XLOOKUP(E38, Products!A:A, Products!E:E, 0) -> 0.08 | K38: =SUM(F38*G38) -> 444 | L38: =SUM(K38*(1-J38)) -> 408.48 | M38: =SUM(K38- (Append1[[#This Row],[Quantity]]*Append1[[#This Row],[UnitCost]]) - Finance!B42) -> 250 | N38: =IF(K38>50000, "VIP", IF(K38>=20000, "Regular", "Low Value")) -> Low Value | O38: =INDEX(E38:E127, MATCH(H38, H38:H127, 0)) -> Smartphone | P38: Electronics | Q38: 97 | R38: =_xlfn.XLOOKUP(A38, Operations!A:A, Operations!B:B, "") -> 4
A39: Q2-007 | B39: 45766.596 | C39: East | D39: 1010 | E39: Printer | F39: 5 | G39: 1485 | H39: =_xlfn.XLOOKUP(E39, Products!A:A, Products!B:B, "Not Found") -> Office | I39: =_xlfn.XLOOKUP(E39, Products!A:A, Products!D:D, 0) -> 136 | J39: =_xlfn.XLOOKUP(E39, Products!A:A, Products!E:E, 0) -> 0.1 | K39: =SUM(F39*G39) -> 7425 | L39: =SUM(K39*(1-J39)) -> 6682.5 | M39: =SUM(K39- (Append1[[#This Row],[Quantity]]*Append1[[#This Row],[UnitCost]]) - Finance!B39) -> 6745 | N39: =IF(K39>50000, "VIP", IF(K39>=20000, "Regular", "Low Value")) -> Low Value | O39: =INDEX(E39:E128, MATCH(H39, H39:H128, 0)) -> Printer | P39: Office | Q39: 136 | R39: =_xlfn.XLOOKUP(A39, Operations!A:A, Operations!B:B, "") -> 1
A40: Q2-008 | B40: 45770.167 | C40: East | D40: 1015 | E40: Smartphone | F40: 3 | G40: 1472 | H40: =_xlfn.XLOOKUP(E40, Products!A:A, Products!B:B, "Not Found") -> Electronics | I40: =_xlfn.XLOOKUP(E40, Products!A:A, Products!D:D, 0) -> 97 | J40: =_xlfn.XLOOKUP(E40, Products!A:A, Products!E:E, 0) -> 0.08 | K40: =SUM(F40*G40) -> 4416 | L40: =SUM(K40*(1-J40)) -> 4062.72 | M40: =SUM(K40- (Append1[[#This Row],[Quantity]]*Append1[[#This Row],[UnitCost]]) - Finance!B40) -> 4125 | N40: =IF(K40>50000, "VIP", IF(K40>=20000, "Regular", "Low Value")) -> Low Value | O40: =INDEX(E40:E129, MATCH(H40, H40:H129, 0)) -> Smartphone | P40: Electronics | Q40: 97 | R40: =_xlfn.XLOOKUP(A40, Operations!A:A, Operations!B:B, "") -> 4
A41: Q2-001 | B41: 45770.272 | C41: North | D41: 1016 | E41: Tablet | F41: 7 | G41: 1039 | H41: =_xlfn.XLOOKUP(E41, Products!A:A, Products!B:B, "Not Found") -> Electronics | I41: =_xlfn.XLOOKUP(E41, Products!A:A, Products!D:D, 0) -> 492 | J41: =_xlfn.XLOOKUP(E41, Products!A:A, Products!E:E, 0) -> 0.14 | K41: =SUM(F41*G41) -> 7273 | L41: =SUM(K41*(1-J41)) -> 6254.78 | M41: =SUM(K41- (Append1[[#This Row],[Quantity]]*Append1[[#This Row],[UnitCost]]) - Finance!B33) -> 3829 | N41: =IF(K41>50000, "VIP", IF(K41>=20000, "Regular", "Low Value")) -> Low Value | O41: =INDEX(E41:E130, MATCH(H41, H41:H130, 0)) -> Tablet | P41: Electronics | Q41: 492 | R41: =_xlfn.XLOOKUP(A41, Operations!A:A, Operations!B:B, "") -> 6
A42: Q2-028 | B42: 45770.85 | C42: East | D42: 1018 | E42: Headphones | F42: 7 | G42: 520 | H42: =_xlfn.XLOOKUP(E42, Products!A:A, Products!B:B, "Not Found") -> Accessories | I42: =_xlfn.XLOOKUP(E42, Products!A:A, Products!D:D, 0) -> 323 | J42: =_xlfn.XLOOKUP(E42, Products!A:A, Products!E:E, 0) -> 0.1 | K42: =SUM(F42*G42) -> 3640 | L42: =SUM(K42*(1-J42)) -> 3276 | M42: =SUM(K42- (Append1[[#This Row],[Quantity]]*Append1[[#This Row],[UnitCost]]) - Finance!B60) -> 1379 | N42: =IF(K42>50000, "VIP", IF(K42>=20000, "Regular", "Low Value")) -> Low Value | O42: =INDEX(E42:E131, MATCH(H42, H42:H131, 0)) -> Headphones | P42: Accessories | Q42: 323 | R42: =_xlfn.XLOOKUP(A42, Operations!A:A, Operations!B:B, "") -> 7
A43: Q2-005 | B43: 45771.115 | C43: North | D43: 1018 | E43: Headphones | F43: 9 | G43: 1259 | H43: =_xlfn.XLOOKUP(E43, Products!A:A, Products!B:B, "Not Found") -> Accessories | I43: =_xlfn.XLOOKUP(E43, Products!A:A, Products!D:D, 0) -> 323 | J43: =_xlfn.XLOOKUP(E43, Products!A:A, Products!E:E, 0) -> 0.1 | K43: =SUM(F43*G43) -> 11331 | L43: =SUM(K43*(1-J43)) -> 10197.9 | M43: =SUM(K43- (Append1[[#This Row],[Quantity]]*Append1[[#This Row],[UnitCost]]) - Finance!B37) -> 8424 | N43: =IF(K43>50000, "VIP", IF(K43>=20000, "Regular", "Low Value")) -> Low Value | O43: =INDEX(E43:E132, MATCH(H43, H43:H132, 0)) -> Headphones | P43: Accessories | Q43: 323 | R43: =_xlfn.XLOOKUP(A43, Operations!A:A, Operations!B:B, "") -> 4
A44: Q2-022 | B44: 45773.566 | C44: West | D44: 1007 | E44: Smartphone | F44: 6 | G44: 1219 | H44: =_xlfn.XLOOKUP(E44, Products!A:A, Products!B:B, "Not Found") -> Electronics | I44: =_xlfn.XLOOKUP(E44, Products!A:A, Products!D:D, 0) -> 97 | J44: =_xlfn.XLOOKUP(E44, Products!A:A, Products!E:E, 0) -> 0.08 | K44: =SUM(F44*G44) -> 7314 | L44: =SUM(K44*(1-J44)) -> 6728.88 | M44: =SUM(K44- (Append1[[#This Row],[Quantity]]*Append1[[#This Row],[UnitCost]]) - Finance!B54) -> 6732 | N44: =IF(K44>50000, "VIP", IF(K44>=20000, "Regular", "Low Value")) -> Low Value | O44: =INDEX(E44:E133, MATCH(H44, H44:H133, 0)) -> Smartphone | P44: Electronics | Q44: 97 | R44: =_xlfn.XLOOKUP(A44, Operations!A:A, Operations!B:B, "") -> 3
A45: Q2-003 | B45: 45774.625 | C45: West | D45: 1014 | E45: Monitor | F45: 5 | G45: 1951 | H45: =_xlfn.XLOOKUP(E45, Products!A:A, Products!B:B, "Not Found") -> Electronics | I45: =_xlfn.XLOOKUP(E45, Products!A:A, Products!D:D, 0) -> 463 | J45: =_xlfn.XLOOKUP(E45, Products!A:A, Products!E:E, 0) -> 0.23 | K45: =SUM(F45*G45) -> 9755 | L45: =SUM(K45*(1-J45)) -> 7511.35 | M45: =SUM(K45- (Append1[[#This Row],[Quantity]]*Append1[[#This Row],[UnitCost]]) - Finance!B35) -> 7440 | N45: =IF(K45>50000, "VIP", IF(K45>=20000, "Regular", "Low Value")) -> Low Value | O45: =INDEX(E45:E134, MATCH(H45, H45:H134, 0)) -> Monitor | P45: Electronics | Q45: 463 | R45: =_xlfn.XLOOKUP(A45, Operations!A:A, Operations!B:B, "") -> 3
A46: Q2-027 | B46: 45782.08 | C46: North | D46: 1009 | E46: Smartphone | F46: 9 | G46: 249 | H46: =_xlfn.XLOOKUP(E46, Products!A:A, Products!B:B, "Not Found") -> Electronics | I46: =_xlfn.XLOOKUP(E46, Products!A:A, Products!D:D, 0) -> 97 | J46: =_xlfn.XLOOKUP(E46, Products!A:A, Products!E:E, 0) -> 0.08 | K46: =SUM(F46*G46) -> 2241 | L46: =SUM(K46*(1-J46)) -> 2061.72 | M46: =SUM(K46- (Append1[[#This Row],[Quantity]]*Append1[[#This Row],[UnitCost]]) - Finance!B59) -> 1368 | N46: =IF(K46>50000, "VIP", IF(K46>=20000, "Regular", "Low Value")) -> Low Value | O46: =INDEX(E46:E135, MATCH(H46, H46:H135, 0)) -> Smartphone | P46: Electronics | Q46: 97 | R46: =_xlfn.XLOOKUP(A46, Operations!A:A, Operations!B:B, "") -> 7
A47: Q2-017 | B47: 45787.814 | C47: North | D47: 1009 | E47: Printer | F47: 1 | G47: 398 | H47: =_xlfn.XLOOKUP(E47, Products!A:A, Products!B:B, "Not Found") -> Office | I47: =_xlfn.XLOOKUP(E47, Products!A:A, Products!D:D, 0) -> 136 | J47: =_xlfn.XLOOKUP(E47, Products!A:A, Products!E:E, 0) -> 0.1 | K47: =SUM(F47*G47) -> 398 | L47: =SUM(K47*(1-J47)) -> 358.2 | M47: =SUM(K47- (Append1[[#This Row],[Quantity]]*Append1[[#This Row],[UnitCost]]) - Finance!B49) -> 262 | N47: =IF(K47>50000, "VIP", IF(K47>=20000, "Regular", "Low Value")) -> Low Value | O47: =INDEX(E47:E136, MATCH(H47, H47:H136, 0)) -> Printer | P47: Office | Q47: 136 | R47: =_xlfn.XLOOKUP(A47, Operations!A:A, Operations!B:B, "") -> 5
A48: Q2-015 | B48: 45788.261 | C48: North | D48: 1013 | E48: Printer | F48: 2 | G48: 1414 | H48: =_xlfn.XLOOKUP(E48, Products!A:A, Products!B:B, "Not Found") -> Office | I48: =_xlfn.XLOOKUP(E48, Products!A:A, Products!D:D, 0) -> 136 | J48: =_xlfn.XLOOKUP(E48, Products!A:A, Products!E:E, 0) -> 0.1 | K48: =SUM(F48*G48) -> 2828 | L48: =SUM(K48*(1-J48)) -> 2545.2 | M48: =SUM(K48- (Append1[[#This Row],[Quantity]]*Append1[[#This Row],[UnitCost]]) - Finance!B47) -> 2556 | N48: =IF(K48>50000, "VIP", IF(K48>=20000, "Regular", "Low Value")) -> Low Value | O48: =INDEX(E48:E137, MATCH(H48, H48:H137, 0)) -> Printer | P48: Office | Q48: 136 | R48: =_xlfn.XLOOKUP(A48, Operations!A:A, Operations!B:B, "") -> 1
A49: Q2-016 | B49: 45789.088 | C49: East | D49: 1011 | E49: Headphones | F49: 9 | G49: 1076 | H49: =_xlfn.XLOOKUP(E49, Products!A:A, Products!B:B, "Not Found") -> Accessories | I49: =_xlfn.XLOOKUP(E49, Products!A:A, Products!D:D, 0) -> 323 | J49: =_xlfn.XLOOKUP(E49, Products!A:A, Products!E:E, 0) -> 0.1 | K49: =SUM(F49*G49) -> 9684 | L49: =SUM(K49*(1-J49)) -> 8715.6 | M49: =SUM(K49- (Append1[[#This Row],[Quantity]]*Append1[[#This Row],[UnitCost]]) - Finance!B48) -> 6777 | N49: =IF(K49>50000, "VIP", IF(K49>=20000, "Regular", "Low Value")) -> Low Value | O49: =INDEX(E49:E138, MATCH(H49, H49:H138, 0)) -> Headphones | P49: Accessories | Q49: 323 | R49: =_xlfn.XLOOKUP(A49, Operations!A:A, Operations!B:B, "") -> 5
A50: Q2-004 | B50: 45789.476 | C50: South | D50: 1009 | E50: Smartphone | F50: 1 | G50: 1187 | H50: =_xlfn.XLOOKUP(E50, Products!A:A, Products!B:B, "Not Found") -> Electronics | I50: =_xlfn.XLOOKUP(E50, Products!A:A, Products!D:D, 0) -> 97 | J50: =_xlfn.XLOOKUP(E50, Products!A:A, Products!E:E, 0) -> 0.08 | K50: =SUM(F50*G50) -> 1187 | L50: =SUM(K50*(1-J50)) -> 1092.04 | M50: =SUM(K50- (Append1[[#This Row],[Quantity]]*Append1[[#This Row],[UnitCost]]) - Finance!B36) -> 1090 | N50: =IF(K50>50000, "VIP", IF(K50>=20000, "Regular", "Low Value")) -> Low Value | O50: =INDEX(E50:E139, MATCH(H50, H50:H139, 0)) -> Smartphone | P50: Electronics | Q50: 97 | R50: =_xlfn.XLOOKUP(A50, Operations!A:A, Operations!B:B, "") -> 9
A51: Q2-024 | B51: 45790.06 | C51: West | D51: 1019 | E51: Headphones | F51: 4 | G51: 1964 | H51: =_xlfn.XLOOKUP(E51, Products!A:A, Products!B:B, "Not Found") -> Accessories | I51: =_xlfn.XLOOKUP(E51, Products!A:A, Products!D:D, 0) -> 323 | J51: =_xlfn.XLOOKUP(E51, Products!A:A, Products!E:E, 0) -> 0.1 | K51: =SUM(F51*G51) -> 7856 | L51: =SUM(K51*(1-J51)) -> 7070.4 | M51: =SUM(K51- (Append1[[#This Row],[Quantity]]*Append1[[#This Row],[UnitCost]]) - Finance!B56) -> 6564 | N51: =IF(K51>50000, "VIP", IF(K51>=20000, "Regular", "Low Value")) -> Low Value | O51: =INDEX(E51:E140, MATCH(H51, H51:H140, 0)) -> Headphones | P51: Accessories | Q51: 323 | R51: =_xlfn.XLOOKUP(A51, Operations!A:A, Operations!B:B, "") -> 3
A52: Q2-023 | B52: 45790.725 | C52: South | D52: 1020 | E52: Printer | F52: 2 | G52: 1169 | H52: =_xlfn.XLOOKUP(E52, Products!A:A, Products!B:B, "Not Found") -> Office | I52: =_xlfn.XLOOKUP(E52, Products!A:A, Products!D:D, 0) -> 136 | J52: =_xlfn.XLOOKUP(E52, Products!A:A, Products!E:E, 0) -> 0.1 | K52: =SUM(F52*G52) -> 2338 | L52: =SUM(K52*(1-J52)) -> 2104.2 | M52: =SUM(K52- (Append1[[#This Row],[Quantity]]*Append1[[#This Row],[UnitCost]]) - Finance!B55) -> 2066 | N52: =IF(K52>50000, "VIP", IF(K52>=20000, "Regular", "Low Value")) -> Low Value | O52: =INDEX(E52:E141, MATCH(H52, H52:H141, 0)) -> Printer | P52: Office | Q52: 136 | R52: =_xlfn.XLOOKUP(A52, Operations!A:A, Operations!B:B, "") -> 5
A53: Q2-025 | B53: 45797.921 | C53: West | D53: 1002 | E53: Tablet | F53: 4 | G53: 1929 | H53: =_xlfn.XLOOKUP(E53, Products!A:A, Products!B:B, "Not Found") -> Electronics | I53: =_xlfn.XLOOKUP(E53, Products!A:A, Products!D:D, 0) -> 492 | J53: =_xlfn.XLOOKUP(E53, Products!A:A, Products!E:E, 0) -> 0.14 | K53: =SUM(F53*G53) -> 7716 | L53: =SUM(K53*(1-J53)) -> 6635.76 | M53: =SUM(K53- (Append1[[#This Row],[Quantity]]*Append1[[#This Row],[UnitCost]]) - Finance!B57) -> 5748 | N53: =IF(K53>50000, "VIP", IF(K53>=20000, "Regular", "Low Value")) -> Low Value | O53: =INDEX(E53:E142, MATCH(H53, H53:H142, 0)) -> Tablet | P53: Electronics | Q53: 492 | R53: =_xlfn.XLOOKUP(A53, Operations!A:A, Operations!B:B, "") -> 8
A54: Q2-018 | B54: 45807.765 | C54: East | D54: 1003 | E54: Headphones | F54: 8 | G54: 1684 | H54: =_xlfn.XLOOKUP(E54, Products!A:A, Products!B:B, "Not Found") -> Accessories | I54: =_xlfn.XLOOKUP(E54, Products!A:A, Products!D:D, 0) -> 323 | J54: =_xlfn.XLOOKUP(E54, Products!A:A, Products!E:E, 0) -> 0.1 | K54: =SUM(F54*G54) -> 13472 | L54: =SUM(K54*(1-J54)) -> 12124.8 | M54: =SUM(K54- (Append1[[#This Row],[Quantity]]*Append1[[#This Row],[UnitCost]]) - Finance!B50) -> 10888 | N54: =IF(K54>50000, "VIP", IF(K54>=20000, "Regular", "Low Value")) -> Low Value | O54: =INDEX(E54:E143, MATCH(H54, H54:H143, 0)) -> Headphones | P54: Accessories | Q54: 323 | R54: =_xlfn.XLOOKUP(A54, Operations!A:A, Operations!B:B, "") -> 6
A55: Q2-029 | B55: 45811.9 | C55: South | D55: 1007 | E55: Monitor | F55: 9 | G55: 854 | H55: =_xlfn.XLOOKUP(E55, Products!A:A, Products!B:B, "Not Found") -> Electronics | I55: =_xlfn.XLOOKUP(E55, Products!A:A, Products!D:D, 0) -> 463 | J55: =_xlfn.XLOOKUP(E55, Products!A:A, Products!E:E, 0) -> 0.23 | K55: =SUM(F55*G55) -> 7686 | L55: =SUM(K55*(1-J55)) -> 5918.22 | M55: =SUM(K55- (Append1[[#This Row],[Quantity]]*Append1[[#This Row],[UnitCost]]) - Finance!B61) -> 3519 | N55: =IF(K55>50000, "VIP", IF(K55>=20000, "Regular", "Low Value")) -> Low Value | O55: =INDEX(E55:E144, MATCH(H55, H55:H144, 0)) -> Monitor | P55: Electronics | Q55: 463 | R55: =_xlfn.XLOOKUP(A55, Operations!A:A, Operations!B:B, "") -> 1
A56: Q2-020 | B56: 45816.867 | C56: East | D56: 1006 | E56: Laptop | F56: 6 | G56: 634 | H56: =_xlfn.XLOOKUP(E56, Products!A:A, Products!B:B, "Not Found") -> Electronics | I56: =_xlfn.XLOOKUP(E56, Products!A:A, Products!D:D, 0) -> 469 | J56: =_xlfn.XLOOKUP(E56, Products!A:A, Products!E:E, 0) -> 0.22 | K56: =SUM(F56*G56) -> 3804 | L56: =SUM(K56*(1-J56)) -> 2967.12 | M56: =SUM(K56- (Append1[[#This Row],[Quantity]]*Append1[[#This Row],[UnitCost]]) - Finance!B52) -> 990 | N56: =IF(K56>50000, "VIP", IF(K56>=20000, "Regular", "Low Value")) -> Low Value | O56: =INDEX(E56:E145, MATCH(H56, H56:H145, 0)) -> Laptop | P56: Electronics | Q56: 469 | R56: =_xlfn.XLOOKUP(A56, Operations!A:A, Operations!B:B, "") -> 7
A57: Q2-002 | B57: 45821.985 | C57: West | D57: 1010 | E57: Smartphone | F57: 2 | G57: 809 | H57: =_xlfn.XLOOKUP(E57, Products!A:A, Products!B:B, "Not Found") -> Electronics | I57: =_xlfn.XLOOKUP(E57, Products!A:A, Products!D:D, 0) -> 97 | J57: =_xlfn.XLOOKUP(E57, Products!A:A, Products!E:E, 0) -> 0.08 | K57: =SUM(F57*G57) -> 1618 | L57: =SUM(K57*(1-J57)) -> 1488.56 | M57: =SUM(K57- (Append1[[#This Row],[Quantity]]*Append1[[#This Row],[UnitCost]]) - Finance!B34) -> 1424 | N57: =IF(K57>50000, "VIP", IF(K57>=20000, "Regular", "Low Value")) -> Low Value | O57: =INDEX(E57:E146, MATCH(H57, H57:H146, 0)) -> Smartphone | P57: Electronics | Q57: 97 | R57: =_xlfn.XLOOKUP(A57, Operations!A:A, Operations!B:B, "") -> 5
A58: Q2-012 | B58: 45823.74 | C58: West | D58: 1001 | E58: Headphones | F58: 2 | G58: 1545 | H58: =_xlfn.XLOOKUP(E58, Products!A:A, Products!B:B, "Not Found") -> Accessories | I58: =_xlfn.XLOOKUP(E58, Products!A:A, Products!D:D, 0) -> 323 | J58: =_xlfn.XLOOKUP(E58, Products!A:A, Products!E:E, 0) -> 0.1 | K58: =SUM(F58*G58) -> 3090 | L58: =SUM(K58*(1-J58)) -> 2781 | M58: =SUM(K58- (Append1[[#This Row],[Quantity]]*Append1[[#This Row],[UnitCost]]) - Finance!B44) -> 2444 | N58: =IF(K58>50000, "VIP", IF(K58>=20000, "Regular", "Low Value")) -> Low Value | O58: =INDEX(E58:E147, MATCH(H58, H58:H147, 0)) -> Headphones | P58: Accessories | Q58: 323 | R58: =_xlfn.XLOOKUP(A58, Operations!A:A, Operations!B:B, "") -> 8
A59: Q2-013 | B59: 45827.39 | C59: East | D59: 1019 | E59: Laptop | F59: 1 | G59: 1437 | H59: =_xlfn.XLOOKUP(E59, Products!A:A, Products!B:B, "Not Found") -> Electronics | I59: =_xlfn.XLOOKUP(E59, Products!A:A, Products!D:D, 0) -> 469 | J59: =_xlfn.XLOOKUP(E59, Products!A:A, Products!E:E, 0) -> 0.22 | K59: =SUM(F59*G59) -> 1437 | L59: =SUM(K59*(1-J59)) -> 1120.86 | M59: =SUM(K59- (Append1[[#This Row],[Quantity]]*Append1[[#This Row],[UnitCost]]) - Finance!B45) -> 968 | N59: =IF(K59>50000, "VIP", IF(K59>=20000, "Regular", "Low Value")) -> Low Value | O59: =INDEX(E59:E148, MATCH(H59, H59:H148, 0)) -> Laptop | P59: Electronics | Q59: 469 | R59: =_xlfn.XLOOKUP(A59, Operations!A:A, Operations!B:B, "") -> 7
A60: Q2-006 | B60: 45833.931 | C60: North | D60: 1010 | E60: Monitor | F60: 6 | G60: 1460 | H60: =_xlfn.XLOOKUP(E60, Products!A:A, Products!B:B, "Not Found") -> Electronics | I60: =_xlfn.XLOOKUP(E60, Products!A:A, Products!D:D, 0) -> 463 | J60: =_xlfn.XLOOKUP(E60, Products!A:A, Products!E:E, 0) -> 0.23 | K60: =SUM(F60*G60) -> 8760 | L60: =SUM(K60*(1-J60)) -> 6745.2 | M60: =SUM(K60- (Append1[[#This Row],[Quantity]]*Append1[[#This Row],[UnitCost]]) - Finance!B38) -> 5982 | N60: =IF(K60>50000, "VIP", IF(K60>=20000, "Regular", "Low Value")) -> Low Value | O60: =INDEX(E60:E149, MATCH(H60, H60:H149, 0)) -> Monitor | P60: Electronics | Q60: 463 | R60: =_xlfn.XLOOKUP(A60, Operations!A:A, Operations!B:B, "") -> 6
A61: Q2-021 | B61: 45835.86 | C61: West | D61: 1007 | E61: Laptop | F61: 3 | G61: 119 | H61: =_xlfn.XLOOKUP(E61, Products!A:A, Products!B:B, "Not Found") -> Electronics | I61: =_xlfn.XLOOKUP(E61, Products!A:A, Products!D:D, 0) -> 469 | J61: =_xlfn.XLOOKUP(E61, Products!A:A, Products!E:E, 0) -> 0.22 | K61: =SUM(F61*G61) -> 357 | L61: =SUM(K61*(1-J61)) -> 278.46 | M61: =SUM(K61- (Append1[[#This Row],[Quantity]]*Append1[[#This Row],[UnitCost]]) - Finance!B53) -> -1050 | N61: =IF(K61>50000, "VIP", IF(K61>=20000, "Regular", "Low Value")) -> Low Value | O61: =INDEX(E61:E150, MATCH(H61, H61:H150, 0)) -> Laptop | P61: Electronics | Q61: 469 | R61: =_xlfn.XLOOKUP(A61, Operations!A:A, Operations!B:B, "") -> 7
A62: Q3-001 | B62: 45839.828 | C62: North | D62: 1001 | E62: Monitor | F62: 4 | G62: 160 | H62: =_xlfn.XLOOKUP(E62, Products!A:A, Products!B:B, "Not Found") -> Electronics | I62: =_xlfn.XLOOKUP(E62, Products!A:A, Products!D:D, 0) -> 463 | J62: =_xlfn.XLOOKUP(E62, Products!A:A, Products!E:E, 0) -> 0.23 | K62: =SUM(F62*G62) -> 640 | L62: =SUM(K62*(1-J62)) -> 492.8 | M62: =SUM(K62- (Append1[[#This Row],[Quantity]]*Append1[[#This Row],[UnitCost]]) - Finance!B63) -> -1212 | N62: =IF(K62>50000, "VIP", IF(K62>=20000, "Regular", "Low Value")) -> Low Value | O62: =INDEX(E62:E151, MATCH(H62, H62:H151, 0)) -> Monitor | P62: Electronics | Q62: 463 | R62: =_xlfn.XLOOKUP(A62, Operations!A:A, Operations!B:B, "") -> 3
A63: Q3-022 | B63: 45841.351 | C63: North | D63: 1012 | E63: Monitor | F63: 1 | G63: 1186 | H63: =_xlfn.XLOOKUP(E63, Products!A:A, Products!B:B, "Not Found") -> Electronics | I63: =_xlfn.XLOOKUP(E63, Products!A:A, Products!D:D, 0) -> 463 | J63: =_xlfn.XLOOKUP(E63, Products!A:A, Products!E:E, 0) -> 0.23 | K63: =SUM(F63*G63) -> 1186 | L63: =SUM(K63*(1-J63)) -> 913.22 | M63: =SUM(K63- (Append1[[#This Row],[Quantity]]*Append1[[#This Row],[UnitCost]]) - Finance!B84) -> 723 | N63: =IF(K63>50000, "VIP", IF(K63>=20000, "Regular", "Low Value")) -> Low Value | O63: =INDEX(E63:E152, MATCH(H63, H63:H152, 0)) -> Monitor | P63: Electronics | Q63: 463 | R63: =_xlfn.XLOOKUP(A63, Operations!A:A, Operations!B:B, "") -> 8
A64: Q3-004 | B64: 45844.234 | C64: East | D64: 1019 | E64: Laptop | F64: 3 | G64: 603 | H64: =_xlfn.XLOOKUP(E64, Products!A:A, Products!B:B, "Not Found") -> Electronics | I64: =_xlfn.XLOOKUP(E64, Products!A:A, Products!D:D, 0) -> 469 | J64: =_xlfn.XLOOKUP(E64, Products!A:A, Products!E:E, 0) -> 0.22 | K64: =SUM(F64*G64) -> 1809 | L64: =SUM(K64*(1-J64)) -> 1411.02 | M64: =SUM(K64- (Append1[[#This Row],[Quantity]]*Append1[[#This Row],[UnitCost]]) - Finance!B66) -> 402 | N64: =IF(K64>50000, "VIP", IF(K64>=20000, "Regular", "Low Value")) -> Low Value | O64: =INDEX(E64:E153, MATCH(H64, H64:H153, 0)) -> Laptop | P64: Electronics | Q64: 469 | R64: =_xlfn.XLOOKUP(A64, Operations!A:A, Operations!B:B, "") -> 5
A65: Q3-014 | B65: 45849.52 | C65: West | D65: 1005 | E65: Tablet | F65: 8 | G65: 1707 | H65: =_xlfn.XLOOKUP(E65, Products!A:A, Products!B:B, "Not Found") -> Electronics | I65: =_xlfn.XLOOKUP(E65, Products!A:A, Products!D:D, 0) -> 492 | J65: =_xlfn.XLOOKUP(E65, Products!A:A, Products!E:E, 0) -> 0.14 | K65: =SUM(F65*G65) -> 13656 | L65: =SUM(K65*(1-J65)) -> 11744.16 | M65: =SUM(K65- (Append1[[#This Row],[Quantity]]*Append1[[#This Row],[UnitCost]]) - Finance!B76) -> 9720 | N65: =IF(K65>50000, "VIP", IF(K65>=20000, "Regular", "Low Value")) -> Low Value | O65: =INDEX(E65:E154, MATCH(H65, H65:H154, 0)) -> Tablet | P65: Electronics | Q65: 492 | R65: =_xlfn.XLOOKUP(A65, Operations!A:A, Operations!B:B, "") -> 6
A66: Q3-005 | B66: 45850.673 | C66: South | D66: 1006 | E66: Monitor | F66: 8 | G66: 1987 | H66: =_xlfn.XLOOKUP(E66, Products!A:A, Products!B:B, "Not Found") -> Electronics | I66: =_xlfn.XLOOKUP(E66, Products!A:A, Products!D:D, 0) -> 463 | J66: =_xlfn.XLOOKUP(E66, Products!A:A, Products!E:E, 0) -> 0.23 | K66: =SUM(F66*G66) -> 15896 | L66: =SUM(K66*(1-J66)) -> 12239.92 | M66: =SUM(K66- (Append1[[#This Row],[Quantity]]*Append1[[#This Row],[UnitCost]]) - Finance!B67) -> 12192 | N66: =IF(K66>50000, "VIP", IF(K66>=20000, "Regular", "Low Value")) -> Low Value | O66: =INDEX(E66:E155, MATCH(H66, H66:H155, 0)) -> Monitor | P66: Electronics | Q66: 463 | R66: =_xlfn.XLOOKUP(A66, Operations!A:A, Operations!B:B, "") -> 3
A67: Q3-008 | B67: 45857.335 | C67: South | D67: 1015 | E67: Smartphone | F67: 4 | G67: 1461 | H67: =_xlfn.XLOOKUP(E67, Products!A:A, Products!B:B, "Not Found") -> Electronics | I67: =_xlfn.XLOOKUP(E67, Products!A:A, Products!D:D, 0) -> 97 | J67: =_xlfn.XLOOKUP(E67, Products!A:A, Products!E:E, 0) -> 0.08 | K67: =SUM(F67*G67) -> 5844 | L67: =SUM(K67*(1-J67)) -> 5376.48 | M67: =SUM(K67- (Append1[[#This Row],[Quantity]]*Append1[[#This Row],[UnitCost]]) - Finance!B70) -> 5456 | N67: =IF(K67>50000, "VIP", IF(K67>=20000, "Regular", "Low Value")) -> Low Value | O67: =INDEX(E67:E156, MATCH(H67, H67:H156, 0)) -> Smartphone | P67: Electronics | Q67: 97 | R67: =_xlfn.XLOOKUP(A67, Operations!A:A, Operations!B:B, "") -> 8
A68: Q3-026 | B68: 45858.36 | C68: West | D68: 1017 | E68: Smartphone | F68: 9 | G68: 472 | H68: =_xlfn.XLOOKUP(E68, Products!A:A, Products!B:B, "Not Found") -> Electronics | I68: =_xlfn.XLOOKUP(E68, Products!A:A, Products!D:D, 0) -> 97 | J68: =_xlfn.XLOOKUP(E68, Products!A:A, Products!E:E, 0) -> 0.08 | K68: =SUM(F68*G68) -> 4248 | L68: =SUM(K68*(1-J68)) -> 3908.16 | M68: =SUM(K68- (Append1[[#This Row],[Quantity]]*Append1[[#This Row],[UnitCost]]) - Finance!B88) -> 3375 | N68: =IF(K68>50000, "VIP", IF(K68>=20000, "Regular", "Low Value")) -> Low Value | O68: =INDEX(E68:E157, MATCH(H68, H68:H157, 0)) -> Smartphone | P68: Electronics | Q68: 97 | R68: =_xlfn.XLOOKUP(A68, Operations!A:A, Operations!B:B, "") -> 1
A69: Q3-002 | B69: 45859.5 | C69: South | D69: 1001 | E69: Monitor | F69: 1 | G69: 233 | H69: =_xlfn.XLOOKUP(E69, Products!A:A, Products!B:B, "Not Found") -> Electronics | I69: =_xlfn.XLOOKUP(E69, Products!A:A, Products!D:D, 0) -> 463 | J69: =_xlfn.XLOOKUP(E69, Products!A:A, Products!E:E, 0) -> 0.23 | K69: =SUM(F69*G69) -> 233 | L69: =SUM(K69*(1-J69)) -> 179.41 | M69: =SUM(K69- (Append1[[#This Row],[Quantity]]*Append1[[#This Row],[UnitCost]]) - Finance!B64) -> -230 | N69: =IF(K69>50000, "VIP", IF(K69>=20000, "Regular", "Low Value")) -> Low Value | O69: =INDEX(E69:E158, MATCH(H69, H69:H158, 0)) -> Monitor | P69: Electronics | Q69: 463 | R69: =_xlfn.XLOOKUP(A69, Operations!A:A, Operations!B:B, "") -> 4
A70: Q3-028 | B70: 45861.291 | C70: North | D70: 1018 | E70: Laptop | F70: 4 | G70: 1817 | H70: =_xlfn.XLOOKUP(E70, Products!A:A, Products!B:B, "Not Found") -> Electronics | I70: =_xlfn.XLOOKUP(E70, Products!A:A, Products!D:D, 0) -> 469 | J70: =_xlfn.XLOOKUP(E70, Products!A:A, Products!E:E, 0) -> 0.22 | K70: =SUM(F70*G70) -> 7268 | L70: =SUM(K70*(1-J70)) -> 5669.04 | M70: =SUM(K70- (Append1[[#This Row],[Quantity]]*Append1[[#This Row],[UnitCost]]) - Finance!B90) -> 5392 | N70: =IF(K70>50000, "VIP", IF(K70>=20000, "Regular", "Low Value")) -> Low Value | O70: =INDEX(E70:E159, MATCH(H70, H70:H159, 0)) -> Laptop | P70: Electronics | Q70: 469 | R70: =_xlfn.XLOOKUP(A70, Operations!A:A, Operations!B:B, "") -> 3
A71: Q3-027 | B71: 45862.545 | C71: East | D71: 1002 | E71: Laptop | F71: 9 | G71: 132 | H71: =_xlfn.XLOOKUP(E71, Products!A:A, Products!B:B, "Not Found") -> Electronics | I71: =_xlfn.XLOOKUP(E71, Products!A:A, Products!D:D, 0) -> 469 | J71: =_xlfn.XLOOKUP(E71, Products!A:A, Products!E:E, 0) -> 0.22 | K71: =SUM(F71*G71) -> 1188 | L71: =SUM(K71*(1-J71)) -> 926.64 | M71: =SUM(K71- (Append1[[#This Row],[Quantity]]*Append1[[#This Row],[UnitCost]]) - Finance!B89) -> -3033 | N71: =IF(K71>50000, "VIP", IF(K71>=20000, "Regular", "Low Value")) -> Low Value | O71: =INDEX(E71:E160, MATCH(H71, H71:H160, 0)) -> Laptop | P71: Electronics | Q71: 469 | R71: =_xlfn.XLOOKUP(A71, Operations!A:A, Operations!B:B, "") -> 7
A72: Q3-019 | B72: 45867.799 | C72: West | D72: 1017 | E72: Laptop | F72: 8 | G72: 1150 | H72: =_xlfn.XLOOKUP(E72, Products!A:A, Products!B:B, "Not Found") -> Electronics | I72: =_xlfn.XLOOKUP(E72, Products!A:A, Products!D:D, 0) -> 469 | J72: =_xlfn.XLOOKUP(E72, Products!A:A, Products!E:E, 0) -> 0.22 | K72: =SUM(F72*G72) -> 9200 | L72: =SUM(K72*(1-J72)) -> 7176 | M72: =SUM(K72- (Append1[[#This Row],[Quantity]]*Append1[[#This Row],[UnitCost]]) - Finance!B81) -> 5448 | N72: =IF(K72>50000, "VIP", IF(K72>=20000, "Regular", "Low Value")) -> Low Value | O72: =INDEX(E72:E161, MATCH(H72, H72:H161, 0)) -> Laptop | P72: Electronics | Q72: 469 | R72: =_xlfn.XLOOKUP(A72, Operations!A:A, Operations!B:B, "") -> 3
A73: Q3-012 | B73: 45868.096 | C73: West | D73: 1011 | E73: Tablet | F73: 3 | G73: 1634 | H73: =_xlfn.XLOOKUP(E73, Products!A:A, Products!B:B, "Not Found") -> Electronics | I73: =_xlfn.XLOOKUP(E73, Products!A:A, Products!D:D, 0) -> 492 | J73: =_xlfn.XLOOKUP(E73, Products!A:A, Products!E:E, 0) -> 0.14 | K73: =SUM(F73*G73) -> 4902 | L73: =SUM(K73*(1-J73)) -> 4215.72 | M73: =SUM(K73- (Append1[[#This Row],[Quantity]]*Append1[[#This Row],[UnitCost]]) - Finance!B74) -> 3426 | N73: =IF(K73>50000, "VIP", IF(K73>=20000, "Regular", "Low Value")) -> Low Value | O73: =INDEX(E73:E162, MATCH(H73, H73:H162, 0)) -> Tablet | P73: Electronics | Q73: 492 | R73: =_xlfn.XLOOKUP(A73, Operations!A:A, Operations!B:B, "") -> 7
A74: Q3-015 | B74: 45873.099 | C74: North | D74: 1004 | E74: Laptop | F74: 4 | G74: 960 | H74: =_xlfn.XLOOKUP(E74, Products!A:A, Products!B:B, "Not Found") -> Electronics | I74: =_xlfn.XLOOKUP(E74, Products!A:A, Products!D:D, 0) -> 469 | J74: =_xlfn.XLOOKUP(E74, Products!A:A, Products!E:E, 0) -> 0.22 | K74: =SUM(F74*G74) -> 3840 | L74: =SUM(K74*(1-J74)) -> 2995.2 | M74: =SUM(K74- (Append1[[#This Row],[Quantity]]*Append1[[#This Row],[UnitCost]]) - Finance!B77) -> 1964 | N74: =IF(K74>50000, "VIP", IF(K74>=20000, "Regular", "Low Value")) -> Low Value | O74: =INDEX(E74:E163, MATCH(H74, H74:H163, 0)) -> Laptop | P74: Electronics | Q74: 469 | R74: =_xlfn.XLOOKUP(A74, Operations!A:A, Operations!B:B, "") -> 7
A75: Q3-023 | B75: 45874.123 | C75: East | D75: 1001 | E75: Laptop | F75: 6 | G75: 272 | H75: =_xlfn.XLOOKUP(E75, Products!A:A, Products!B:B, "Not Found") -> Electronics | I75: =_xlfn.XLOOKUP(E75, Products!A:A, Products!D:D, 0) -> 469 | J75: =_xlfn.XLOOKUP(E75, Products!A:A, Products!E:E, 0) -> 0.22 | K75: =SUM(F75*G75) -> 1632 | L75: =SUM(K75*(1-J75)) -> 1272.96 | M75: =SUM(K75- (Append1[[#This Row],[Quantity]]*Append1[[#This Row],[UnitCost]]) - Finance!B85) -> -1182 | N75: =IF(K75>50000, "VIP", IF(K75>=20000, "Regular", "Low Value")) -> Low Value | O75: =INDEX(E75:E164, MATCH(H75, H75:H164, 0)) -> Laptop | P75: Electronics | Q75: 469 | R75: =_xlfn.XLOOKUP(A75, Operations!A:A, Operations!B:B, "") -> 2
A76: Q3-024 | B76: 45875.451 | C76: South | D76: 1014 | E76: Headphones | F76: 9 | G76: 1794 | H76: =_xlfn.XLOOKUP(E76, Products!A:A, Products!B:B, "Not Found") -> Accessories | I76: =_xlfn.XLOOKUP(E76, Products!A:A, Products!D:D, 0) -> 323 | J76: =_xlfn.XLOOKUP(E76, Products!A:A, Products!E:E, 0) -> 0.1 | K76: =SUM(F76*G76) -> 16146 | L76: =SUM(K76*(1-J76)) -> 14531.4 | M76: =SUM(K76- (Append1[[#This Row],[Quantity]]*Append1[[#This Row],[UnitCost]]) - Finance!B86) -> 13239 | N76: =IF(K76>50000, "VIP", IF(K76>=20000, "Regular", "Low Value")) -> Low Value | O76: =INDEX(E76:E165, MATCH(H76, H76:H165, 0)) -> Headphones | P76: Accessories | Q76: 323 | R76: =_xlfn.XLOOKUP(A76, Operations!A:A, Operations!B:B, "") -> 6
A77: Q3-020 | B77: 45880.702 | C77: North | D77: 1019 | E77: Tablet | F77: 2 | G77: 508 | H77: =_xlfn.XLOOKUP(E77, Products!A:A, Products!B:B, "Not Found") -> Electronics | I77: =_xlfn.XLOOKUP(E77, Products!A:A, Products!D:D, 0) -> 492 | J77: =_xlfn.XLOOKUP(E77, Products!A:A, Products!E:E, 0) -> 0.14 | K77: =SUM(F77*G77) -> 1016 | L77: =SUM(K77*(1-J77)) -> 873.76 | M77: =SUM(K77- (Append1[[#This Row],[Quantity]]*Append1[[#This Row],[UnitCost]]) - Finance!B82) -> 32 | N77: =IF(K77>50000, "VIP", IF(K77>=20000, "Regular", "Low Value")) -> Low Value | O77: =INDEX(E77:E166, MATCH(H77, H77:H166, 0)) -> Tablet | P77: Electronics | Q77: 492 | R77: =_xlfn.XLOOKUP(A77, Operations!A:A, Operations!B:B, "") -> 4
A78: Q3-007 | B78: 45886.322 | C78: East | D78: 1006 | E78: Headphones | F78: 2 | G78: 1742 | H78: =_xlfn.XLOOKUP(E78, Products!A:A, Products!B:B, "Not Found") -> Accessories | I78: =_xlfn.XLOOKUP(E78, Products!A:A, Products!D:D, 0) -> 323 | J78: =_xlfn.XLOOKUP(E78, Products!A:A, Products!E:E, 0) -> 0.1 | K78: =SUM(F78*G78) -> 3484 | L78: =SUM(K78*(1-J78)) -> 3135.6 | M78: =SUM(K78- (Append1[[#This Row],[Quantity]]*Append1[[#This Row],[UnitCost]]) - Finance!B69) -> 2838 | N78: =IF(K78>50000, "VIP", IF(K78>=20000, "Regular", "Low Value")) -> Low Value | O78: =INDEX(E78:E167, MATCH(H78, H78:H167, 0)) -> Headphones | P78: Accessories | Q78: 323 | R78: =_xlfn.XLOOKUP(A78, Operations!A:A, Operations!B:B, "") -> 4
A79: Q3-029 | B79: 45889.658 | C79: North | D79: 1019 | E79: Monitor | F79: 5 | G79: 698 | H79: =_xlfn.XLOOKUP(E79, Products!A:A, Products!B:B, "Not Found") -> Electronics | I79: =_xlfn.XLOOKUP(E79, Products!A:A, Products!D:D, 0) -> 463 | J79: =_xlfn.XLOOKUP(E79, Products!A:A, Products!E:E, 0) -> 0.23 | K79: =SUM(F79*G79) -> 3490 | L79: =SUM(K79*(1-J79)) -> 2687.3 | M79: =SUM(K79- (Append1[[#This Row],[Quantity]]*Append1[[#This Row],[UnitCost]]) - Finance!B91) -> 1175 | N79: =IF(K79>50000, "VIP", IF(K79>=20000, "Regular", "Low Value")) -> Low Value | O79: =INDEX(E79:E168, MATCH(H79, H79:H168, 0)) -> Monitor | P79: Electronics | Q79: 463 | R79: =_xlfn.XLOOKUP(A79, Operations!A:A, Operations!B:B, "") -> 4
A80: Q3-006 | B80: 45891.791 | C80: North | D80: 1008 | E80: Laptop | F80: 3 | G80: 589 | H80: =_xlfn.XLOOKUP(E80, Products!A:A, Products!B:B, "Not Found") -> Electronics | I80: =_xlfn.XLOOKUP(E80, Products!A:A, Products!D:D, 0) -> 469 | J80: =_xlfn.XLOOKUP(E80, Products!A:A, Products!E:E, 0) -> 0.22 | K80: =SUM(F80*G80) -> 1767 | L80: =SUM(K80*(1-J80)) -> 1378.26 | M80: =SUM(K80- (Append1[[#This Row],[Quantity]]*Append1[[#This Row],[UnitCost]]) - Finance!B68) -> 360 | N80: =IF(K80>50000, "VIP", IF(K80>=20000, "Regular", "Low Value")) -> Low Value | O80: =INDEX(E80:E169, MATCH(H80, H80:H169, 0)) -> Laptop | P80: Electronics | Q80: 469 | R80: =_xlfn.XLOOKUP(A80, Operations!A:A, Operations!B:B, "") -> 5
A81: Q3-003 | B81: 45894.505 | C81: West | D81: 1010 | E81: Smartphone | F81: 9 | G81: 312 | H81: =_xlfn.XLOOKUP(E81, Products!A:A, Products!B:B, "Not Found") -> Electronics | I81: =_xlfn.XLOOKUP(E81, Products!A:A, Products!D:D, 0) -> 97 | J81: =_xlfn.XLOOKUP(E81, Products!A:A, Products!E:E, 0) -> 0.08 | K81: =SUM(F81*G81) -> 2808 | L81: =SUM(K81*(1-J81)) -> 2583.36 | M81: =SUM(K81- (Append1[[#This Row],[Quantity]]*Append1[[#This Row],[UnitCost]]) - Finance!B65) -> 1935 | N81: =IF(K81>50000, "VIP", IF(K81>=20000, "Regular", "Low Value")) -> Low Value | O81: =INDEX(E81:E170, MATCH(H81, H81:H170, 0)) -> Smartphone | P81: Electronics | Q81: 97 | R81: =_xlfn.XLOOKUP(A81, Operations!A:A, Operations!B:B, "") -> 6
A82: Q3-025 | B82: 45895.845 | C82: South | D82: 1006 | E82: Monitor | F82: 5 | G82: 757 | H82: =_xlfn.XLOOKUP(E82, Products!A:A, Products!B:B, "Not Found") -> Electronics | I82: =_xlfn.XLOOKUP(E82, Products!A:A, Products!D:D, 0) -> 463 | J82: =_xlfn.XLOOKUP(E82, Products!A:A, Products!E:E, 0) -> 0.23 | K82: =SUM(F82*G82) -> 3785 | L82: =SUM(K82*(1-J82)) -> 2914.45 | M82: =SUM(K82- (Append1[[#This Row],[Quantity]]*Append1[[#This Row],[UnitCost]]) - Finance!B87) -> 1470 | N82: =IF(K82>50000, "VIP", IF(K82>=20000, "Regular", "Low Value")) -> Low Value | O82: =INDEX(E82:E171, MATCH(H82, H82:H171, 0)) -> Monitor | P82: Electronics | Q82: 463 | R82: =_xlfn.XLOOKUP(A82, Operations!A:A, Operations!B:B, "") -> 4
A83: Q3-011 | B83: 45897.155 | C83: North | D83: 1002 | E83: Headphones | F83: 2 | G83: 1265 | H83: =_xlfn.XLOOKUP(E83, Products!A:A, Products!B:B, "Not Found") -> Accessories | I83: =_xlfn.XLOOKUP(E83, Products!A:A, Products!D:D, 0) -> 323 | J83: =_xlfn.XLOOKUP(E83, Products!A:A, Products!E:E, 0) -> 0.1 | K83: =SUM(F83*G83) -> 2530 | L83: =SUM(K83*(1-J83)) -> 2277 | M83: =SUM(K83- (Append1[[#This Row],[Quantity]]*Append1[[#This Row],[UnitCost]]) - Finance!B73) -> 1884 | N83: =IF(K83>50000, "VIP", IF(K83>=20000, "Regular", "Low Value")) -> Low Value | O83: =INDEX(E83:E172, MATCH(H83, H83:H172, 0)) -> Headphones | P83: Accessories | Q83: 323 | R83: =_xlfn.XLOOKUP(A83, Operations!A:A, Operations!B:B, "") -> 6
A84: Q3-030 | B84: 45898.259 | C84: West | D84: 1003 | E84: Monitor | F84: 3 | G84: 651 | H84: =_xlfn.XLOOKUP(E84, Products!A:A, Products!B:B, "Not Found") -> Electronics | I84: =_xlfn.XLOOKUP(E84, Products!A:A, Products!D:D, 0) -> 463 | J84: =_xlfn.XLOOKUP(E84, Products!A:A, Products!E:E, 0) -> 0.23 | K84: =SUM(F84*G84) -> 1953 | L84: =SUM(K84*(1-J84)) -> 1503.81 | M84: =SUM(K84- (Append1[[#This Row],[Quantity]]*Append1[[#This Row],[UnitCost]]) - Finance!B92) -> 564 | N84: =IF(K84>50000, "VIP", IF(K84>=20000, "Regular", "Low Value")) -> Low Value | O84: =INDEX(E84:E173, MATCH(H84, H84:H173, 0)) -> Monitor | P84: Electronics | Q84: 463 | R84: =_xlfn.XLOOKUP(A84, Operations!A:A, Operations!B:B, "") -> 5
A85: Q3-017 | B85: 45906.443 | C85: South | D85: 1017 | E85: Printer | F85: 2 | G85: 300 | H85: =_xlfn.XLOOKUP(E85, Products!A:A, Products!B:B, "Not Found") -> Office | I85: =_xlfn.XLOOKUP(E85, Products!A:A, Products!D:D, 0) -> 136 | J85: =_xlfn.XLOOKUP(E85, Products!A:A, Products!E:E, 0) -> 0.1 | K85: =SUM(F85*G85) -> 600 | L85: =SUM(K85*(1-J85)) -> 540 | M85: =SUM(K85- (Append1[[#This Row],[Quantity]]*Append1[[#This Row],[UnitCost]]) - Finance!B79) -> 328 | N85: =IF(K85>50000, "VIP", IF(K85>=20000, "Regular", "Low Value")) -> Low Value | O85: =INDEX(E85:E174, MATCH(H85, H85:H174, 0)) -> Printer | P85: Office | Q85: 136 | R85: =_xlfn.XLOOKUP(A85, Operations!A:A, Operations!B:B, "") -> 8
A86: Q3-018 | B86: 45911.79 | C86: West | D86: 1001 | E86: Laptop | F86: 7 | G86: 608 | H86: =_xlfn.XLOOKUP(E86, Products!A:A, Products!B:B, "Not Found") -> Electronics | I86: =_xlfn.XLOOKUP(E86, Products!A:A, Products!D:D, 0) -> 469 | J86: =_xlfn.XLOOKUP(E86, Products!A:A, Products!E:E, 0) -> 0.22 | K86: =SUM(F86*G86) -> 4256 | L86: =SUM(K86*(1-J86)) -> 3319.68 | M86: =SUM(K86- (Append1[[#This Row],[Quantity]]*Append1[[#This Row],[UnitCost]]) - Finance!B80) -> 973 | N86: =IF(K86>50000, "VIP", IF(K86>=20000, "Regular", "Low Value")) -> Low Value | O86: =INDEX(E86:E175, MATCH(H86, H86:H175, 0)) -> Laptop | P86: Electronics | Q86: 469 | R86: =_xlfn.XLOOKUP(A86, Operations!A:A, Operations!B:B, "") -> 4
A87: Q3-009 | B87: 45914.314 | C87: South | D87: 1002 | E87: Laptop | F87: 3 | G87: 1133 | H87: =_xlfn.XLOOKUP(E87, Products!A:A, Products!B:B, "Not Found") -> Electronics | I87: =_xlfn.XLOOKUP(E87, Products!A:A, Products!D:D, 0) -> 469 | J87: =_xlfn.XLOOKUP(E87, Products!A:A, Products!E:E, 0) -> 0.22 | K87: =SUM(F87*G87) -> 3399 | L87: =SUM(K87*(1-J87)) -> 2651.22 | M87: =SUM(K87- (Append1[[#This Row],[Quantity]]*Append1[[#This Row],[UnitCost]]) - Finance!B71) -> 1992 | N87: =IF(K87>50000, "VIP", IF(K87>=20000, "Regular", "Low Value")) -> Low Value | O87: =INDEX(E87:E176, MATCH(H87, H87:H176, 0)) -> Laptop | P87: Electronics | Q87: 469 | R87: =_xlfn.XLOOKUP(A87, Operations!A:A, Operations!B:B, "") -> 1
A88: Q3-013 | B88: 45916.958 | C88: East | D88: 1012 | E88: Printer | F88: 3 | G88: 144 | H88: =_xlfn.XLOOKUP(E88, Products!A:A, Products!B:B, "Not Found") -> Office | I88: =_xlfn.XLOOKUP(E88, Products!A:A, Products!D:D, 0) -> 136 | J88: =_xlfn.XLOOKUP(E88, Products!A:A, Products!E:E, 0) -> 0.1 | K88: =SUM(F88*G88) -> 432 | L88: =SUM(K88*(1-J88)) -> 388.8 | M88: =SUM(K88- (Append1[[#This Row],[Quantity]]*Append1[[#This Row],[UnitCost]]) - Finance!B75) -> 24 | N88: =IF(K88>50000, "VIP", IF(K88>=20000, "Regular", "Low Value")) -> Low Value | O88: =INDEX(E88:E177, MATCH(H88, H88:H177, 0)) -> Printer | P88: Office | Q88: 136 | R88: =_xlfn.XLOOKUP(A88, Operations!A:A, Operations!B:B, "") -> 7
A89: Q3-016 | B89: 45926.223 | C89: West | D89: 1017 | E89: Laptop | F89: 5 | G89: 1416 | H89: =_xlfn.XLOOKUP(E89, Products!A:A, Products!B:B, "Not Found") -> Electronics | I89: =_xlfn.XLOOKUP(E89, Products!A:A, Products!D:D, 0) -> 469 | J89: =_xlfn.XLOOKUP(E89, Products!A:A, Products!E:E, 0) -> 0.22 | K89: =SUM(F89*G89) -> 7080 | L89: =SUM(K89*(1-J89)) -> 5522.4 | M89: =SUM(K89- (Append1[[#This Row],[Quantity]]*Append1[[#This Row],[UnitCost]]) - Finance!B78) -> 4735 | N89: =IF(K89>50000, "VIP", IF(K89>=20000, "Regular", "Low Value")) -> Low Value | O89: =INDEX(E89:E178, MATCH(H89, H89:H178, 0)) -> Laptop | P89: Electronics | Q89: 469 | R89: =_xlfn.XLOOKUP(A89, Operations!A:A, Operations!B:B, "") -> 5
A90: Q3-021 | B90: 45926.246 | C90: South | D90: 1019 | E90: Tablet | F90: 1 | G90: 1272 | H90: =_xlfn.XLOOKUP(E90, Products!A:A, Products!B:B, "Not Found") -> Electronics | I90: =_xlfn.XLOOKUP(E90, Products!A:A, Products!D:D, 0) -> 492 | J90: =_xlfn.XLOOKUP(E90, Products!A:A, Products!E:E, 0) -> 0.14 | K90: =SUM(F90*G90) -> 1272 | L90: =SUM(K90*(1-J90)) -> 1093.92 | M90: =SUM(K90- (Append1[[#This Row],[Quantity]]*Append1[[#This Row],[UnitCost]]) - Finance!B83) -> 780 | N90: =IF(K90>50000, "VIP", IF(K90>=20000, "Regular", "Low Value")) -> Low Value | O90: =INDEX(E90:E179, MATCH(H90, H90:H179, 0)) -> Tablet | P90: Electronics | Q90: 492 | R90: =_xlfn.XLOOKUP(A90, Operations!A:A, Operations!B:B, "") -> 9
A91: Q3-010 | B91: 45926.582 | C91: East | D91: 1018 | E91: Monitor | F91: 5 | G91: 644 | H91: =_xlfn.XLOOKUP(E91, Products!A:A, Products!B:B, "Not Found") -> Electronics | I91: =_xlfn.XLOOKUP(E91, Products!A:A, Products!D:D, 0) -> 463 | J91: =_xlfn.XLOOKUP(E91, Products!A:A, Products!E:E, 0) -> 0.23 | K91: =SUM(F91*G91) -> 3220 | L91: =SUM(K91*(1-J91)) -> 2479.4 | M91: =SUM(K91- (Append1[[#This Row],[Quantity]]*Append1[[#This Row],[UnitCost]]) - Finance!B72) -> 905 | N91: =IF(K91>50000, "VIP", IF(K91>=20000, "Regular", "Low Value")) -> Low Value | O91: =INDEX(E91:E180, MATCH(H91, H91:H180, 0)) -> Monitor | P91: Electronics | Q91: 463 | R91: =_xlfn.XLOOKUP(A91, Operations!A:A, Operations!B:B, "") -> 1
P92: 0 | Q92: 0
P93: 0 | Q93: 0
P94: 0 | Q94: 0
B95: UNIQUE LIST | D95: ORDERS | F95: DELIVERY | P95: 0 | Q95: 0
B96: {=_xlfn.UNIQUE(C2:C91)} -> North | D96: =COUNTIF(C:C, B96) -> 22 | F96: =AVERAGEIF(C:C,B96,R:R) -> 4.5909091 | P96: 0 | Q96: 0
B97: West | D97: =COUNTIF(C:C, B97) -> 24 | F97: =AVERAGEIF(C:C,B97,R:R) -> 5.0833333 | P97: 0 | Q97: 0
B98: South | D98: =COUNTIF(C:C, B98) -> 23 | F98: =AVERAGEIF(C:C,B98,R:R) -> 5.4347826 | P98: 0 | Q98: 0
B99: East | D99: =COUNTIF(C:C, B99) -> 21 | F99: =AVERAGEIF(C:C,B99,R:R) -> 4.3809524 | P99: 0 | Q99: 0
P100: 0 | Q100: 0
...

Sheet Dashboard
A1: TotalRevenue | B1: TotalProfit | C1: TopCustomer
A2: =SUM(Append1[Discounted Revenue]) -> 370395.88 | B2: =SUM(Append1[Profit]) -> -192490 | C2: =INDEX(Sales_All!D2:D91, MATCH(MAX(Sales_All!L2:L91), Sales_All!L2:L91, 0)) -> 1017
A4: Count of Product | B4: Column Labels
A5: Row Labels | B5: East | C5: North | D5: South | E5: West | F5: Grand Total
A6: Accessories | B6: 6 | C6: 4 | D6: 4 | E6: 3 | F6: 17
A7: Electronics | B7: 11 | C7: 13 | D7: 15 | E7: 19 | F7: 58
A8: Office | B8: 4 | C8: 5 | D8: 4 | E8: 2 | F8: 15
A9: Grand Total | B9: 21 | C9: 22 | D9: 23 | E9: 24 | F9: 90

Sheet Customers
A1: CustomerID | B1: FirstName | C1: LastName | D1: Email | E1: Region | F1: Standardized | G1: Extracted First Name | H1: Extracted Last Name | I1: Extracted Email
A2: 1001 | B2: Naledi | C2: Pillay | D2: naledi.pillay@example.com | E2: East | F2: Naledi Pillay | G2: Naledi | H2: Pillay | I2: example.com
A3: 1002 | B3: Michael | C3: van Wyk | D3: michael.van wyk@example.com | E3: East | F3: Michael Van Wyk | G3: Michael | H3: van | I3: example.com
A4: 1003 | B4: Naledi | C4: Botha | D4: naledi.botha@example.com | E4: East | F4: Naledi Botha | G4: Naledi | H4: Botha | I4: example.com
A5: 1004 | B5: Naledi | C5: Botha | D5: naledi.botha@example.com | E5: North | F5: Naledi Botha | G5: Naledi | H5: Botha | I5: example.com
A6: 1005 | B6: Michael | C6: Johnson | D6: michael.johnson@example.com | E6: North | F6: Michael Johnson | G6: Michael | H6: Johnson | I6: example.com
A7: 1006 | B7: Emily | C7: Johnson | D7: emily.johnson@example.com | E7: South | F7: Emily Johnson | G7: Emily | H7: Johnson | I7: example.com
A8: 1007 | B8: Michael | C8: Nguyen | D8: michael.nguyen@example.com | E8: West | F8: Michael Nguyen | G8: Michael | H8: Nguyen | I8: example.com
A9: 1008 | B9: Sipho | C9: Johnson | D9: sipho.johnson@example.com | E9: East | F9: Sipho Johnson | G9: Sipho | H9: Johnson | I9: example.com
A10: 1009 | B10: Sarah | C10: Nguyen | D10: sarah.nguyen@example.com | E10: North | F10: Sarah Nguyen | G10: Sarah | H10: Nguyen | I10: example.com
A11: 1010 | B11: John | C11: Brown | D11: john.brown@example.com | E11: East | F11: John Brown | G11: John | H11: Brown | I11: example.com
A12: 1011 | B12: John | C12: Smith | D12: john.smith@example.com | E12: South | F12: John Smith | G12: John | H12: Smith | I12: example.com
A13: 1012 | B13: Naledi | C13: van Wyk | D13: naledi.van wyk@example.com | E13: East | F13: Naledi Van Wyk | G13: Naledi | H13: van | I13: example.com
... A29: 1018 | B29: Michael | C29: Mlambo | D29: michael.mlambo@example.com | E29: South | F29: Michael Mlambo | G29: Michael | H29: Mlambo | I29: example.com

Sheet Products
A1: Product | B1: Category | C1: UnitPrice | D1: UnitCost | E1: Discount
A2: Laptop | B2: Electronics | C2: 1299 | D2: 469 | E2: 0.22
A3: Tablet | B3: Electronics | C3: 1613 | D3: 492 | E3: 0.14
A4: Smartphone | B4: Electronics | C4: 1402 | D4: 97 | E4: 0.08
A5: Headphones | B5: Accessories | C5: 106 | D5: 323 | E5: 0.1
A6: Monitor | B6: Electronics | C6: 396 | D6: 463 | E6: 0.23
A7: Printer | B7: Office | C7: 1635 | D7: 136 | E7: 0.1
A9: DYNAMIC RANGE
A10: {=OFFSET($A$2,0,0,COUNTA($A:$A)-1,2)} -> Laptop | B10: Electronics
A11: Tablet | B11: Electronics
A12: Smartphone | B12: Electronics
A13: Headphones | B13: Accessories
A14: Monitor | B14: Electronics
A15: Printer | B15: Office
A16: 0 | B16: 0

Sheet Operations
A1: OrderID | B1: DeliveryDays | C1: ReturnRate | D1: Operational Efficiency
A2: Q1-001 | B2: 5 | C2: 0.01 | D2: =IF(AND(B2<=3,C2<=0.05),"Efficient", "Needs Attention") -> Needs Attention
A3: Q1-002 | B3: 2 | C3: 0.03 | D3: =IF(AND(B3<=3,C3<=0.05),"Efficient", "Needs Attention") -> Efficient
A4: Q1-003 | B4: 6 | C4: 0.05 | D4: =IF(AND(B4<=3,C4<=0.05),"Efficient", "Needs Attention") -> Needs Attention
A5: Q1-004 | B5: 4 | C5: 0.07 | D5: =IF(AND(B5<=3,C5<=0.05),"Efficient", "Needs Attention") -> Needs Attention
A6: Q1-005 | B6: 5 | C6: 0.03 | D6: =IF(AND(B6<=3,C6<=0.05),"Efficient", "Needs Attention") -> Needs Attention
A7: Q1-006 | B7: 5 | C7: 0.06 | D7: =IF(AND(B7<=3,C7<=0.05),"Efficient", "Needs Attention") -> Needs Attention
A8: Q1-007 | B8: 4 | C8: 0.02 | D8: =IF(AND(B8<=3,C8<=0.05),"Efficient", "Needs Attention") -> Needs Attention
A9: Q1-008 | B9: 8 | C9: 0.07 | D9: =IF(AND(B9<=3,C9<=0.05),"Efficient", "Needs Attention") -> Needs Attention
A10: Q1-009 | B10: 2 | C10: 0.08 | D10: =IF(AND(B10<=3,C10<=0.05),"Efficient", "Needs Attention") -> Needs Attention
A11: Q1-010 | B11: 2 | C11: 0.08 | D11: =IF(AND(B11<=3,C11<=0.05),"Efficient", "Needs Attention") -> Needs Attention
A12: Q1-011 | B12: 8 | C12: 0.06 | D12: =IF(AND(B12<=3,C12<=0.05),"Efficient", "Needs Attention") -> Needs Attention
A13: Q1-012 | B13: 8 | C13: 0.03 | D13: =IF(AND(B13<=3,C13<=0.05),"Efficient", "Needs Attention") -> Needs Attention
... A91: Q3-030 | B91: 5 | C91: 0.09 | D91: =IF(AND(B91<=3,C91<=0.05),"Efficient", "Needs Attention") -> Needs Attention

Sheet Finance
A1: Month | B1: Overheads | C1: Salaries | D1: OtherExpenses | E1: NetProfit
A2: 45688 | B2: 25640 | C2: 60082 | D2: 21492 | E2: =SUM(B2:C2) -> 85722
A3: 45716 | B3: 43320 | C3: 70533 | D3: 27724 | E3: =SUM(B3:C3) -> 113853
A4: 45747 | B4: 34147 | C4: 63890 | D4: 17738 | E4: =SUM(B4:C4) -> 98037
A5: 45777 | B5: 44423 | C5: 90674 | D5: 21152 | E5: =SUM(B5:C5) -> 135097
A6: 45808 | B6: 32119 | C6: 55646 | D6: 19723 | E6: =SUM(B6:C6) -> 87765
A7: 45838 | B7: 20079 | C7: 99954 | D7: 15769 | E7: =SUM(B7:C7) -> 120033
A8: 45869 | B8: 36304 | C8: 63297 | D8: 25453 | E8: =SUM(B8:C8) -> 99601
A9: 45900 | B9: 36734 | C9: 93760 | D9: 16230 | E9: =SUM(B9:C9) -> 130494
A10: 45930 | B10: 34260 | C10: 70760 | D10: 28818 | E10: =SUM(B10:C10) -> 105020

Sheet Sales_Q1
A1: OrderID | B1: Date | C1: Region | D1: CustomerID | E1: Product | F1: Quantity | G1: UnitPrice
A2: Q1-001 | B2: 45708.027 | C2: South | D2: 1018 | E2: Tablet | F2: 1 | G2: 730
A3: Q1-002 | B3: 45712.237 | C3: South | D3: 1004 | E3: Headphones | F3: 3 | G3: 378
A4: Q1-003 | B4: 45736.268 | C4: West | D4: 1005 | E4: Monitor | F4: 1 | G4: 585
A5: Q1-004 | B5: 45703.571 | C5: East | D5: 1018 | E5: Smartphone | F5: 8 | G5: 726
A6: Q1-005 | B6: 45663.686 | C6: North | D6: 1012 | E6: Laptop | F6: 2 | G6: 709
A7: Q1-006 | B7: 45716.227 | C7: East | D7: 1013 | E7: Laptop | F7: 8 | G7: 1817
A8: Q1-007 | B8: 45735.116 | C8: South | D8: 1017 | E8: Tablet | F8: 9 | G8: 1976
A9: Q1-008 | B9: 45707.394 | C9: South | D9: 1014 | E9: Tablet | F9: 5 | G9: 1134
A10: Q1-009 | B10: 45671.497 | C10: South | D10: 1020 | E10: Printer | F10: 1 | G10: 1220
A11: Q1-010 | B11: 45743.202 | C11: West | D11: 1010 | E11: Headphones | F11: 2 | G11: 283
A12: Q1-011 | B12: 45684.929 | C12: West | D12: 1019 | E12: Laptop | F12: 9 | G12: 417
A13: Q1-012 | B13: 45662.79 | C13: South | D13: 1016 | E13: Laptop | F13: 3 | G13: 1692
... A31: Q1-030 | B31: 45666.628 | C31: East | D31: 1016 | E31: Monitor | F31: 5 | G31: 1119

Sheet Sales_Q2
A1: OrderID | B1: Date | C1: Region | D1: CustomerID | E1: Product | F1: Quantity | G1: UnitPrice
A2: Q2-001 | B2: 45770.272 | C2: North | D2: 1016 | E2: Tablet | F2: 7 | G2: 1039
A3: Q2-002 | B3: 45821.985 | C3: West | D3: 1010 | E3: Smartphone | F3: 2 | G3: 809
A4: Q2-003 | B4: 45774.625 | C4: West | D4: 1014 | E4: Monitor | F4: 5 | G4: 1951
A5: Q2-004 | B5: 45789.476 | C5: South | D5: 1009 | E5: Smartphone | F5: 1 | G5: 1187
A6: Q2-005 | B6: 45771.115 | C6: North | D6: 1018 | E6: Headphones | F6: 9 | G6: 1259
A7: Q2-006 | B7: 45833.931 | C7: North | D7: 1010 | E7: Monitor | F7: 6 | G7: 1460
A8: Q2-007 | B8: 45766.596 | C8: East | D8: 1010 | E8: Printer | F8: 5 | G8: 1485
A9: Q2-008 | B9: 45770.167 | C9: East | D9: 1015 | E9: Smartphone | F9: 3 | G9: 1472
A10: Q2-009 | B10: 45759.132 | C10: West | D10: 1020 | E10: Laptop | F10: 8 | G10: 1331
A11: Q2-010 | B11: 45760.76 | C11: West | D11: 1001 | E11: Smartphone | F11: 2 | G11: 222
A12: Q2-011 | B12: 45754.452 | C12: South | D12: 1012 | E12: Headphones | F12: 3 | G12: 1781
A13: Q2-012 | B13: 45823.74 | C13: West | D13: 1001 | E13: Headphones | F13: 2 | G13: 1545
... A31: Q2-030 | B31: 45752.783 | C31: East | D31: 1006 | E31: Headphones | F31: 2 | G31: 1035

Sheet Sales_Q3
A1: OrderID | B1: Date | C1: Region | D1: CustomerID | E1: Product | F1: Quantity | G1: UnitPrice
A2: Q3-001 | B2: 45839.828 | C2: North | D2: 1001 | E2: Monitor | F2: 4 | G2: 160
A3: Q3-002 | B3: 45859.5 | C3: South | D3: 1001 | E3: Monitor | F3: 1 | G3: 233
A4: Q3-003 | B4: 45894.505 | C4: West | D4: 1010 | E4: Smartphone | F4: 9 | G4: 312
A5: Q3-004 | B5: 45844.234 | C5: East | D5: 1019 | E5: Laptop | F5: 3 | G5: 603
A6: Q3-005 | B6: 45850.673 | C6: South | D6: 1006 | E6: Monitor | F6: 8 | G6: 1987
A7: Q3-006 | B7: 45891.791 | C7: North | D7: 1008 | E7: Laptop | F7: 3 | G7: 589
A8: Q3-007 | B8: 45886.322 | C8: East | D8: 1006 | E8: Headphones | F8: 2 | G8: 1742
A9: Q3-008 | B9: 45857.335 | C9: South | D9: 1015 | E9: Smartphone | F9: 4 | G9: 1461
A10: Q3-009 | B10: 45914.314 | C10: South | D10: 1002 | E10: Laptop | F10: 3 | G10: 1133
A11: Q3-010 | B11: 45926.582 | C11: East | D11: 1018 | E11: Monitor | F11: 5 | G11: 644
A12: Q3-011 | B12: 45897.155 | C12: North | D12: 1002 | E12: Headphones | F12: 2 | G12: 1265
A13: Q3-012 | B13: 45868.096 | C13: West | D13: 1011 | E13: Tablet | F13: 3 | G13: 1634
... A31: Q3-030 | B31: 45898.259 | C31: West | D31: 1003 | E31: Monitor | F31: 3 | G31: 651
